Workbook

Sheet Premissas
A1: Premissas do modelo - Biogas por Codigestao Anaerobia
A2: Todos os valores sao editaveis. A planilha recalcula automaticamente.
A4: ID | B4: Parametro | C4: Valor | D4: Unidade | E4: Fonte | F4: Mini-resumo didatico
A5: P01 | B5: Volume total de mistura | C5: 100 | D5: m3/dia | E5: Base de calculo | F5: Quanto liquido entra no digestor por dia.
A6: P02 | B6: Fracao volumetrica lodo | C6: 0.5 | D6: - | E6: Premissa | F6: Metade do volume vem do lodo de esgoto.
A7: P03 | B7: Fracao volumetrica vinhaca | C7: 0.3 | D7: - | E7: Premissa | F7: 30% do volume e vinhaca de cana.
A8: P04 | B8: Fracao volumetrica residuo organico | C8: 0.2 | D8: - | E8: Premissa | F8: 20% do volume sao residuos organicos.
A9: P05 | B9: Densidade lodo | C9: 1020 | D9: kg/m3 | E9: PROSAB | F9: Massa por litro do lodo.
A10: P06 | B10: Densidade vinhaca | C10: 1009 | D10: kg/m3 | E10: RVQ 2024 | F10: Massa por litro da vinhaca.
A11: P07 | B11: Densidade residuo organico | C11: 1050 | D11: kg/m3 | E11: Literatura | F11: Massa por litro do residuo.
A12: P08 | B12: ST lodo | C12: 3.5 | D12: % | E12: Embrapa 2024 | F12: Solidos totais: tudo que sobra se secar o lodo.
A13: P09 | B13: ST vinhaca | C13: 1.7 | D13: % | E13: RVQ 2024 | F13: Solidos totais da vinhaca; bem diluida.
A14: P10 | B14: ST residuo organico | C14: 20 | D14: % | E14: Literatura | F14: Solidos totais do residuo; concentrado.
A15: P11 | B15: SV/ST lodo | C15: 65 | D15: % | E15: Embrapa | F15: Quanto dos solidos e materia organica no lodo.
A16: P12 | B16: SV/ST vinhaca | C16: 75 | D16: % | E16: Literatura | F16: Quanto dos solidos e materia organica na vinhaca.
... A59: P55 | B59: MM outros gases (media) | C59: 29 | D59: kg/kmol | E59: Premissa | F59: Massa molar media dos gases minoritarios.

Sheet Calculos_Massa
A1: Calculos de massa - Balanco global
A2: Todas as celulas de valor (coluna B) sao formulas que referenciam Premissas.
A4: ID | B4: Valor | C4: Unidade | D4: Mini-resumo didatico
A5: Volume lodo (m3/dia) | B5: =Premissas!C5*Premissas!C6 -> 50 | C5: m3/dia | D5: Volume total x fracao de lodo.
A6: Volume vinhaca (m3/dia) | B6: =Premissas!C5*Premissas!C7 -> 30 | C6: m3/dia | D6: Volume total x fracao de vinhaca.
A7: Volume residuo (m3/dia) | B7: =Premissas!C5*Premissas!C8 -> 20 | C7: m3/dia | D7: Volume total x fracao de residuo.
A8: Massa lodo (kg/dia) | B8: =B5*Premissas!C9 -> 51000 | C8: kg/dia | D8: Volume x densidade do lodo.
A9: Massa vinhaca (kg/dia) | B9: =B6*Premissas!C10 -> 30270 | C9: kg/dia | D9: Volume x densidade da vinhaca.
A10: Massa residuo (kg/dia) | B10: =B7*Premissas!C11 -> 21000 | C10: kg/dia | D10: Volume x densidade do residuo.
A11: Massa total entrada (kg/dia) | B11: =B8+B9+B10 -> 102270 | C11: kg/dia | D11: Soma das tres correntes.
A12: ST lodo (kg/dia) | B12: =B8*Premissas!C12/100 -> 1785 | C12: kg/dia | D12: Massa lodo x %ST.
A13: ST vinhaca (kg/dia) | B13: =B9*Premissas!C13/100 -> 514.59 | C13: kg/dia | D13: Massa vinhaca x %ST.
A14: ST residuo (kg/dia) | B14: =B10*Premissas!C14/100 -> 4200 | C14: kg/dia | D14: Massa residuo x %ST.
A15: ST total entrada (kg/dia) | B15: =B12+B13+B14 -> 6499.59 | C15: kg/dia | D15: Carga solida total.
A16: SV lodo (kg/dia) | B16: =B12*Premissas!C15/100 -> 1160.25 | C16: kg/dia | D16: ST lodo x %SV/ST.
A17: SV vinhaca (kg/dia) | B17: =B13*Premissas!C16/100 -> 385.9425 | C17: kg/dia | D17: ST vinhaca x %SV/ST.
A18: SV residuo (kg/dia) | B18: =B14*Premissas!C17/100 -> 3570 | C18: kg/dia | D18: ST residuo x %SV/ST.
A19: SV total entrada (kg/dia) | B19: =B16+B17+B18 -> 5116.1925 | C19: kg/dia | D19: Materia organica total disponivel.
A20: C/N mistura (ponderada SV) | B20: =(B16*Premissas!C18+B17*Premissas!C19+B18*Premissas!C20)/B19 -> 24.633663 | C20: - | D20: Media ponderada; ideal 20-30.
A21: SV removido (kg/dia) | B21: =B19*Premissas!C39/100 -> 2813.9059 | C21: kg/dia | D21: SV entrada x eficiencia de remocao.
A22: Volume biogas (Nm3/dia) | B22: =B21*Premissas!C40 -> 1688.3435 | C22: Nm3/dia | D22: SV removido x rendimento.
A23: Volume CH4 (Nm3/dia) | B23: =B22*Premissas!C41/100 -> 1046.773 | C23: Nm3/dia | D23: Biogas x %CH4.
A24: Volume CO2 (Nm3/dia) | B24: =B22*Premissas!C42/100 -> 607.80367 | C24: Nm3/dia | D24: Biogas x %CO2.
A25: Volume outros (Nm3/dia) | B25: =B22*Premissas!C43/100 -> 33.766871 | C25: Nm3/dia | D25: Biogas x %outros.
A26: n CH4 (kmol/dia) | B26: =B23/Premissas!C58 -> 46.701748 | C26: kmol/dia | D26: Volume CH4 / volume molar normal.
A27: m CH4 (kg/dia) | B27: =B26*Premissas!C54 -> 747.22797 | C27: kg/dia | D27: n CH4 x MM CH4.
A28: n CO2 (kmol/dia) | B28: =B24/Premissas!C58 -> 27.117144 | C28: kmol/dia | D28: Volume CO2 / volume molar normal.
A29: m CO2 (kg/dia) | B29: =B28*Premissas!C55 -> 1193.1543 | C29: kg/dia | D29: n CO2 x MM CO2.
A30: n outros (kmol/dia) | B30: =B25/Premissas!C58 -> 1.506508 | C30: kmol/dia | D30: Volume outros / volume molar normal.
A31: m outros (kg/dia) | B31: =B30*Premissas!C59 -> 43.688732 | C31: kg/dia | D31: n outros x MM outros.
A32: Massa biogas total (kg/dia) | B32: =B27+B29+B31 -> 1984.071 | C32: kg/dia | D32: Soma CH4 + CO2 + outros.
A33: Volume reator (m3) | B33: =Premissas!C5*Premissas!C38 -> 2000 | C33: m3 | D33: Volume total x TRH.
A34: COV (kgSV/m3.dia) | B34: =B19/B33 -> 2.5580963 | C34: kgSV/m3.dia | D34: SV entrada / volume reator. Faixa: 1-4.
A35: SV residual (kg/dia) | B35: =B19-B21 -> 2302.2866 | C35: kg/dia | D35: SV nao digerido = SV entrada - SV removido.
A36: SF entrada (kg/dia) | B36: =B15-B19 -> 1383.3975 | C36: kg/dia | D36: Solidos fixos = ST - SV.
A37: ST digestato (kg/dia) | B37: =B35+B36 -> 3685.6841 | C37: kg/dia | D37: SV residual + SF.
A38: Massa digestato (kg/dia) | B38: =B11-B32 -> 100285.93 | C38: kg/dia | D38: Massa entrada - massa biogas.

Sheet Fechamento_Elementar
A1: Fechamento elementar C/H/O/N/S
A2: Rastreamento dos elementos quimicos desde a entrada ate biogas e digestato.
A4: Elemento | B4: Lodo (kg/dia) | C4: Vinhaca (kg/dia) | D4: Residuo (kg/dia) | E4: Total entrada (kg/dia) | F4: No biogas (kg/dia) | G4: Residual digestato (kg/dia) | H4: Mini-resumo
A5: C (Carbono) | B5: =Calculos_Massa!B16*Premissas!C21/100 -> 591.7275 | C5: =Calculos_Massa!B17*Premissas!C26/100 -> 165.95528 | D5: =Calculos_Massa!B18*Premissas!C31/100 -> 1713.6 | E5: =B5+C5+D5 -> 2471.2828 | F5: =Calculos_Massa!B26*Premissas!C57+Calculos_Massa!B28*Premissas!C57 -> 885.82671 | G5: =E5-F5 -> 1585.4561 | H5: C no biogas: 12 kg/kmol por cada mol de CH4 e CO2.
A6: H (Hidrogenio) | B6: =Calculos_Massa!B16*Premissas!C22/100 -> 91.65975 | C6: =Calculos_Massa!B17*Premissas!C27/100 -> 25.086262 | D6: =Calculos_Massa!B18*Premissas!C32/100 -> 228.48 | E6: =B6+C6+D6 -> 345.22601 | F6: =Calculos_Massa!B26*4 -> 186.80699 | G6: =E6-F6 -> 158.41902 | H6: H no biogas: 4 kg H por kmol de CH4.
A7: O (Oxigenio) | B7: =Calculos_Massa!B16*Premissas!C23/100 -> 401.4465 | C7: =Calculos_Massa!B17*Premissas!C28/100 -> 177.53355 | D7: =Calculos_Massa!B18*Premissas!C33/100 -> 1499.4 | E7: =B7+C7+D7 -> 2078.3801 | F7: =Calculos_Massa!B28*32 -> 867.74861 | G7: =E7-F7 -> 1210.6314 | H7: O no biogas: 32 kg O por kmol de CO2.
A8: N (Nitrogenio) | B8: =Calculos_Massa!B16*Premissas!C24/100 -> 62.6535 | C8: =Calculos_Massa!B17*Premissas!C29/100 -> 13.507987 | D8: =Calculos_Massa!B18*Premissas!C34/100 -> 114.24 | E8: =B8+C8+D8 -> 190.40149 | F8: 0 | G8: =E8-F8 -> 190.40149 | H8: N permanece no digestato (NH3 no gas desprezado).
A9: S (Enxofre) | B9: =Calculos_Massa!B16*Premissas!C25/100 -> 12.76275 | C9: =Calculos_Massa!B17*Premissas!C30/100 -> 3.859425 | D9: =Calculos_Massa!B18*Premissas!C35/100 -> 14.28 | E9: =B9+C9+D9 -> 30.902175 | F9: 0 | G9: =E9-F9 -> 30.902175 | H9: S permanece no digestato (H2S no gas desprezado).
A10: TOTAL | B10: =SUM(B5:B9) -> 1160.25 | C10: =SUM(C5:C9) -> 385.9425 | D10: =SUM(D5:D9) -> 3570 | E10: =SUM(E5:E9) -> 5116.1925 | F10: =SUM(F5:F9) -> 1940.3823 | G10: =SUM(G5:G9) -> 3175.8102
A12: C/N elementar da mistura (pela composicao): | B12: =E5/E8 -> 12.979325
A13: Nota: diferente do C/N de catalogo (media ponderada ~24.6) porque este e derivado da analise elementar.
A15: % do C de entrada que sai como biogas: | B15: =F5/E5*100 -> 35.844814 | C15: %

Sheet Correntes_PFD
A1: Tabela de correntes - PFD
A2: Cada corrente numerada pode ser conectada no diagrama de fluxo de processo.
A4: Corrente | B4: Descricao | C4: Massa total (kg/dia) | D4: ST (kg/dia) | E4: SV (kg/dia) | F4: Agua+outros (kg/dia) | G4: Mini-resumo
A5: 101 | B5: Lodo de esgoto | C5: =Calculos_Massa!B8 -> 51000 | D5: =Calculos_Massa!B12 -> 1785 | E5: =Calculos_Massa!B16 -> 1160.25 | F5: =C5-D5 -> 49215 | G5: Entrada do lodo; traz N e buffer.
A6: 102 | B6: Vinhaca | C6: =Calculos_Massa!B9 -> 30270 | D6: =Calculos_Massa!B13 -> 514.59 | E6: =Calculos_Massa!B17 -> 385.9425 | F6: =C6-D6 -> 29755.41 | G6: Entrada da vinhaca; traz C e acidez.
A7: 103 | B7: Residuo organico | C7: =Calculos_Massa!B10 -> 21000 | D7: =Calculos_Massa!B14 -> 4200 | E7: =Calculos_Massa!B18 -> 3570 | F7: =C7-D7 -> 16800 | G7: Entrada do residuo; alto SV.
A8: 104 | B8: Mistura alimentada | C8: =Calculos_Massa!B11 -> 102270 | D8: =Calculos_Massa!B15 -> 6499.59 | E8: =Calculos_Massa!B19 -> 5116.1925 | F8: =C8-D8 -> 95770.41 | G8: Soma das 3 correntes; entra no digestor.
A9: 105 | B9: Biogas bruto | C9: =Calculos_Massa!B32 -> 1984.071 | D9: 0 | E9: 0 | F9: =C9 -> 1984.071 | G9: Gas produzido: CH4 + CO2 + tracos.
A10: 106 | B10: Digestato bruto | C10: =Calculos_Massa!B38 -> 100285.93 | D10: =Calculos_Massa!B37 -> 3685.6841 | E10: =Calculos_Massa!B35 -> 2302.2866 | F10: =C10-D10 -> 96600.245 | G10: Lodo estabilizado que sai do digestor.
A11: 107 | B11: CH4 no biogas | C11: =Calculos_Massa!B27 -> 747.22797 | D11: - | E11: - | F11: =C11 -> 747.22797 | G11: Componente combustivel do biogas.
A12: 108 | B12: CO2 no biogas | C12: =Calculos_Massa!B29 -> 1193.1543 | D12: - | E12: - | F12: =C12 -> 1193.1543 | G12: Inerte; diluente do biogas.
A13: 109 | B13: Digestato desaguado (torta) | C13: =Calculos_Massa!B37/Premissas!C53*100 -> 14742.736 | D13: =Calculos_Massa!B37 -> 3685.6841 | E13: =Calculos_Massa!B35 -> 2302.2866 | F13: =C13-D13 -> 11057.052 | G13: Torta a 25% ST apos desaguamento.
A14: 110 | B14: Agua separada do digestato | C14: =C10-C13 -> 85543.192 | D14: 0 | E14: 0 | F14: =C14 -> 85543.192 | G14: Filtrado/centrifugado; retorna ou trata.

Sheet Balanco_Energia
A1: Balanco de energia completo
A2: Inclui calor de reacao anaerobia, aquecimento, perdas, CHP e eletricidade.
A4: Grandeza | B4: Valor | C4: Unidade | D4: Mini-resumo didatico
A5: Q aquecimento mistura | B5: =Calculos_Massa!B11*Premissas!C44*(Premissas!C37-Premissas!C36)/1000 -> 6136.2 | C5: MJ/dia | D5: Massa x Cp x DeltaT. Aquecer de 20 a 35 degC.
A6: Q perdas reator | B6: =B5*Premissas!C45/100 -> 920.43 | C6: MJ/dia | D6: Perdas pelas paredes = 15% do calor de aquecimento.
A7: Q reacao anaerobia | B7: =Premissas!C50*Calculos_Massa!B21 -> 3376.6871 | C7: MJ/dia | D7: Calor exotermico = 1.2 MJ/kgSV removido.
A8: Q demanda termica liquida | B8: =B5+B6-B7 -> 3679.9429 | C8: MJ/dia | D8: Aquecimento + perdas - calor da reacao.
A9: Energia no biogas (PCI) | B9: =Calculos_Massa!B23*Premissas!C46 -> 37474.473 | C9: MJ/dia | D9: Volume CH4 x PCI metano.
A10: E eletrica CHP (MJ/dia) | B10: =B9*Premissas!C47 -> 14240.3 | C10: MJ/dia | D10: Energia biogas x eficiencia eletrica.
A11: E eletrica CHP (kWh/dia) | B11: =B10/3.6 -> 3955.6388 | C11: kWh/dia | D11: Conversao MJ para kWh (1 kWh = 3.6 MJ).
A12: Q calor recuperavel CHP | B12: =B9*Premissas!C48 -> 15739.279 | C12: MJ/dia | D12: Energia biogas x eficiencia termica.
A13: Q excedente termico | B13: =B12-B8 -> 12059.336 | C13: MJ/dia | D13: Calor CHP - demanda. Se > 0, sobra calor.
A14: E auxiliar eletrica | B14: =B11*Premissas!C49 -> 197.78194 | C14: kWh/dia | D14: 5% da eletricidade gerada.
A15: E eletrica liquida | B15: =B11-B14 -> 3757.8569 | C15: kWh/dia | D15: Eletricidade gerada - consumo auxiliar.
A16: Potencia eletrica media | B16: =B15/24 -> 156.57737 | C16: kW | D16: Eletricidade liquida / 24 horas.

Sheet Fermentacao
A1: Etapas da digestao anaerobia - Modelo conceitual
A2: As 4 etapas biologicas e suas contribuicoes para o balanco.
A4: Etapa | B4: O que entra | C4: O que sai | D4: Agentes | E4: Fracao do CH4 | F4: Mini-resumo
A5: 1. Hidrolise | B5: Proteinas, carboidratos, lipideos | C5: Aminoacidos, acucares, ac. graxos | D5: Bacterias hidroliticas (enzimas extracelulares) | E5: 0 | F5: Quebra moleculas grandes; etapa limitante com solidos.
A6: 2. Acidogenese | B6: Aminoacidos, acucares, ac. graxos | C6: Ac. acetico, propionico, butirico, etanol, H2, CO2 | D6: Bacterias acidogenicas (~90% da populacao) | E6: 0 | F6: Gera acidos volateis; risco de acidificacao se muito rapida.
A7: 3. Acetogenese | B7: Ac. propionico, butirico, etanol | C7: Acetato, H2, CO2 | D7: Bacterias acetogenicas (sintrÃ³ficas) | E7: 0 | F7: Prepara substrato para metanogenicas; sensivel a H2.
A8: 4a. Metanogenese acetoclastica | B8: Acetato (CH3COOH) | C8: CH4 + CO2 | D8: Arqueias metanogenicas | E8: ~70% | F8: CH3COOH -> CH4 + CO2. Rota principal.
A9: 4b. Metanogenese hidrogenotrofica | B9: CO2 + H2 | C9: CH4 + H2O | D9: Arqueias metanogenicas | E9: ~30% | F9: CO2 + 4H2 -> CH4 + 2H2O. Rota secundaria.
A10: TOTAL | B10: Materia organica (SV) | C10: Biogas + Digestato | D10: Consorcio microbiano | E10: 1 | F10: SV entrada -> SV removido + SV residual.
A12: Reacoes simplificadas (estequiometria)
A13: Reacao | B13: Equacao | C13: Observacao
A14: Acetoclastica | B14: CH3COOH -> CH4 + CO2 | C14: 1 mol acetato -> 1 mol CH4 + 1 mol CO2
A15: Hidrogenotrofica | B15: CO2 + 4H2 -> CH4 + 2H2O | C15: 1 mol CO2 + 4 mol H2 -> 1 mol CH4 + 2 mol H2O
A16: Global simplificada | B16: C6H12O6 -> 3CH4 + 3CO2 | C16: Glicose como substrato modelo; 1 mol glicose -> 3 mol CH4
A18: Distribuicao de CH4 por rota (estimativa)
A19: Rota | B19: CH4 (Nm3/dia) | C19: CH4 (kg/dia)
A20: Acetoclastica (70%) | B20: =Calculos_Massa!B23*0.7 -> 732.74109 | C20: =Calculos_Massa!B27*0.7 -> 523.05958
A21: Hidrogenotrofica (30%) | B21: =Calculos_Massa!B23*0.3 -> 314.0319 | C21: =Calculos_Massa!B27*0.3 -> 224.16839
A22: TOTAL | B22: =B20+B21 -> 1046.773 | C22: =C20+C21 -> 747.22797

Sheet Verificacoes
A1: Verificacoes de consistencia
A2: Todas as verificacoes devem retornar OK para o modelo ser valido.
A4: Verificacao | B4: Como calcula | C4: Residual | D4: Unidade | E4: Status
A5: Fechamento massa global | B5: Entrada - biogas - digestato | C5: =Calculos_Massa!B11-Calculos_Massa!B32-Calculos_Massa!B38 -> 0 | D5: kg/dia | E5: =IF(ABS(C5)<1,"OK","REVISAR") -> OK
A6: Fechamento ST digestato | B6: SF + SV residual = ST digestato | C6: =Calculos_Massa!B36+Calculos_Massa!B35-Calculos_Massa!B37 -> 0 | D6: kg/dia | E6: =IF(ABS(C6)<0.01,"OK","REVISAR") -> OK
A7: C/N na faixa ideal (20-30) | B7: Catalogo ponderado | C7: =Calculos_Massa!B20 -> 24.633663 | D7: - | E7: =IF(AND(C7>=20,C7<=30),"OK","FORA DA FAIXA") -> OK
A8: COV na faixa tipica (1-4) | B8: SV/Vreator | C8: =Calculos_Massa!B34 -> 2.5580963 | D8: kgSV/m3.dia | E8: =IF(AND(C8>=1,C8<=4),"OK","FORA DA FAIXA") -> OK
A9: Autossuficiencia termica | B9: Calor CHP >= demanda | C9: =Balanco_Energia!B12-Balanco_Energia!B8 -> 12059.336 | D9: MJ/dia | E9: =IF(C9>=0,"OK - autossuficiente","DEFICIT TERMICO") -> OK - autossuficiente
A10: Composicao biogas = 100% | B10: CH4+CO2+outros | C10: =Premissas!C41+Premissas!C42+Premissas!C43 -> 100 | D10: % vol | E10: =IF(ABS(C10-100)<0.01,"OK","REVISAR") -> OK
A11: Composicao elem. lodo = 100% | B11: C+H+O+N+S | C11: =Premissas!C21+Premissas!C22+Premissas!C23+Premissas!C24+Premissas!C25 -> 100 | D11: % SV | E11: =IF(ABS(C11-100)<0.1,"OK","REVISAR") -> OK
A12: Composicao elem. vinhaca = 100% | B12: C+H+O+N+S | C12: =Premissas!C26+Premissas!C27+Premissas!C28+Premissas!C29+Premissas!C30 -> 100 | D12: % SV | E12: =IF(ABS(C12-100)<0.1,"OK","REVISAR") -> OK
A13: Composicao elem. residuo >= 95% | B13: C+H+O+N+S (dif = outros elem) | C13: =Premissas!C31+Premissas!C32+Premissas!C33+Premissas!C34+Premissas!C35 -> 100 | D13: % SV | E13: =IF(C13>=95,"OK","REVISAR") -> OK
A14: Fracoes volumetricas = 1 | B14: Lodo+vinhaca+residuo | C14: =Premissas!C6+Premissas!C7+Premissas!C8 -> 1 | D14: - | E14: =IF(ABS(C14-1)<0.001,"OK","REVISAR") -> OK

Sheet Dicionario_Variaveis
A1: Dicionario de variaveis
A2: Cada variavel usada na planilha, explicada para leigo.
A4: Variavel | B4: Nome simples | C4: Definicao para leigo | D4: Unidade | E4: Formula | F4: Por que importa
A5: ST | B5: Solidos totais | C5: Tudo que sobra se secar completamente. | D5: % ou kg/dia | E5: Lab | F5: Carga solida total.
A6: SV | B6: Solidos volateis | C6: Parcela organica dos solidos. | D6: % ST ou kg/dia | E6: SV=ST*(SV/ST) | F6: Combustivel dos microrganismos.
A7: SF | B7: Solidos fixos | C7: Cinzas e minerais. | D7: kg/dia | E7: SF=ST-SV | F7: Nao e digerida.
A8: C/N | B8: Relacao C/N | C8: Proporcao carbono/nitrogenio. | D8: - | E8: Ponderada | F8: Ideal 20-30.
A9: TRH | B9: Tempo retencao hidraulica | C9: Tempo medio no reator. | D9: dias | E9: V/Q | F9: Curto = digestao incompleta.
A10: COV | B10: Carga organica volumetrica | C10: SV alimentada/volume/dia. | D10: kgSV/m3.dia | E10: SV/V | F10: Alta = sobrecarga.
A11: eta_SV | B11: Eficiencia remocao SV | C11: Fracao digerida. | D11: % ou fracao | E11: Premissa | F11: Desempenho biologico.
A12: Y_bg | B12: Rendimento biogas | C12: Nm3 biogas por kg SV removido. | D12: Nm3/kgSV | E12: Premissa | F12: Liga digestao ao produto.
A13: PCI | B13: Poder calorifico inferior | C13: Energia util da combustao. | D13: MJ/Nm3 | E13: Constante | F13: Transforma CH4 em energia.
A14: CHP | B14: Cogeracao | C14: Maquina: biogas -> eletricidade + calor. | D14: - | E14: Descritivo | F14: Aproveitamento energetico.
A15: Q_aquec | B15: Calor aquecimento | C15: Energia para aquecer a mistura. | D15: MJ/dia | E15: M*Cp*DT | F15: Maior demanda termica.
... A28: m_O,gas | B28: O no biogas | C28: Oxigenio que saiu como gas. | D28: kg/dia | E28: n_CO2*32 | F28: Rastreamento elementar.

Sheet Conceitos
A1: Conceitos utilizados no modelo
A2: Comece por esta aba se quiser entender a intuicao fisica antes das formulas.
A4: Conceito | B4: Definicao simples | C4: Definicao tecnica | D4: Por que aparece na planilha
A5: Digestao anaerobia | B5: Decomposicao sem oxigenio que gera biogas. | C5: Conversao bioquimica de materia organica em CH4 e CO2 por consorcio microbiano. | D5: Processo central do projeto.
A6: Codigestao | B6: Digerir dois ou mais residuos juntos. | C6: Mistura de substratos para equilibrar C/N e aumentar rendimento. | D6: Justifica a mistura lodo+vinhaca+residuo.
A7: Hidrolise | B7: Quebra de moleculas grandes em pequenas. | C7: Enzimas extracelulares rompem polimeros. | D7: Etapa 1; limitante com solidos.
A8: Acidogenese | B8: Monomeros viram acidos organicos. | C8: Bacterias fermentativas produzem acidos volateis. | D8: Etapa 2; gera intermediarios.
A9: Acetogenese | B9: Acidos viram acetato e H2. | C9: Conversao de acidos em acetato e H2. | D9: Etapa 3; prepara para metanogenese.
A10: Metanogenese | B10: Acetato e H2 viram metano. | C10: Arqueias produzem CH4. | D10: Etapa 4; gera o produto util.
A11: Balanco de massa | B11: Tudo que entra tem que sair. | C11: Conservacao de massa no digestor. | D11: Garante entrada = biogas + digestato.
A12: Balanco de energia | B12: Energia nao surge do nada. | C12: 1a Lei da Termodinamica. | D12: Garante viabilidade termica.
A13: Fechamento elementar | B13: Rastrear C, H, O, N, S. | C13: Conservacao dos elementos quimicos. | D13: Verifica consistencia do modelo.
A14: Autossuficiencia termica | B14: Calor do CHP >= demanda? | C14: Balanco termico do processo. | D14: Se sim, nao precisa fonte externa.
A15: Biogas | B15: Gas com CH4 e CO2. | C15: Mistura gasosa combustivel da digestao. | D15: Produto principal.
... A22: Desaguamento | B22: Separar agua do digestato. | C22: Filtro-prensa ou centrifuga. | D22: Reduz volume para destinacao.

Sheet Utilidades
A1: Utilidades do processo
A2: Consumos e producoes de utilidades.
A4: Utilidade | B4: Quantidade | C4: Unidade | D4: Custo (R$/dia) | E4: Mini-resumo
A5: Calor para aquecer mistura | B5: =Balanco_Energia!B5 -> 6136.2 | C5: MJ/dia | D5: =0 -> 0 | E5: Suprido pelo CHP se autossuficiente.
A6: Calor para perdas | B6: =Balanco_Energia!B6 -> 920.43 | C6: MJ/dia | D6: =0 -> 0 | E6: Suprido pelo CHP.
A7: Calor de reacao (credito) | B7: =Balanco_Energia!B7 -> 3376.6871 | C7: MJ/dia | D7: =0 -> 0 | E7: Gerado pela biologia; nao e custo.
A8: Eletricidade auxiliar | B8: =Balanco_Energia!B14 -> 197.78194 | C8: kWh/dia | D8: =B8*Premissas!C51 -> 148.33646 | E8: Consumo interno.
A9: Eletricidade liquida (venda) | B9: =Balanco_Energia!B15 -> 3757.8569 | C9: kWh/dia | D9: =-B9*Premissas!C51 -> -2818.3926 | E9: Receita (negativo = entrada).

Sheet Custos
A1: Custos e receitas conceituais
A2: Valores editaveis; nao substitui orcamento executivo.
A4: Item | B4: Quantidade | C4: Unidade | D4: Custo unit. | E4: Subtotal (R$/dia) | F4: Mini-resumo
A5: Descarte digestato (ST) | B5: =Calculos_Massa!B37 -> 3685.6841 | C5: kg ST/dia | D5: =Premissas!C52 -> 0.3 | E5: =B5*D5 -> 1105.7052 | F5: Custo de destinacao dos solidos.
A6: Consumo eletrico auxiliar | B6: =Balanco_Energia!B14 -> 197.78194 | C6: kWh/dia | D6: =Premissas!C51 -> 0.75 | E6: =B6*D6 -> 148.33646 | F6: Energia interna do sistema.
A7: Receita de eletricidade | B7: =Balanco_Energia!B15 -> 3757.8569 | C7: kWh/dia | D7: =Premissas!C51 -> 0.75 | E7: =-B7*D7 -> -2818.3926 | F7: Receita (valor negativo).
A8: Agua de processo | B8: =Calculos_Massa!B11*0.001 -> 102.27 | C8: m3/dia | D8: =2 -> 2 | E8: =B8*D8 -> 204.54 | F8: Estimativa agua de selagem e limpeza.
A9: Manutencao (% investimento/dia) | B9: =1 -> 1 | C9: verba/dia | D9: =500 -> 500 | E9: =B9*D9 -> 500 | F9: Manutencao preventiva.
A11: Saldo operacional diario | E11: =SUM(E5:E9) -> -859.81096

Sheet PFD_Visual
A1: PFD Visual - Diagrama de fluxo simplificado
A2: Representacao em texto do fluxo de processo.
A4: [101] LODO DE ESGOTO
A5: |
A6: v
A7: [102] VINHACA ------> [TANQUE DE MISTURA] ---[104]---> [DIGESTOR ANAEROBIO] ---[105]---> BIOGAS
A8: ^ | |---[107]---> CH4 (combustivel)
A9: | | |---[108]---> CO2 (inerte)
A10: [103] RESIDUO ORG. |
A11: v
A12: [106] DIGESTATO
A13: |
... A19: Correntes principais (valores)
A20: Corrente | B20: Massa (kg/dia) | C20: Descricao
A21: =Correntes_PFD!A5 -> 101 | B21: =Correntes_PFD!C5 -> 51000 | C21: =Correntes_PFD!B5 -> Lodo de esgoto
A22: =Correntes_PFD!A6 -> 102 | B22: =Correntes_PFD!C6 -> 30270 | C22: =Correntes_PFD!B6 -> Vinhaca
A23: =Correntes_PFD!A7 -> 103 | B23: =Correntes_PFD!C7 -> 21000 | C23: =Correntes_PFD!B7 -> Residuo organico
A24: =Correntes_PFD!A8 -> 104 | B24: =Correntes_PFD!C8 -> 102270 | C24: =Correntes_PFD!B8 -> Mistura alimentada
A25: =Correntes_PFD!A9 -> 105 | B25: =Correntes_PFD!C9 -> 1984.071 | C25: =Correntes_PFD!B9 -> Biogas bruto
A26: =Correntes_PFD!A10 -> 106 | B26: =Correntes_PFD!C10 -> 100285.93 | C26: =Correntes_PFD!B10 -> Digestato bruto
A27: =Correntes_PFD!A11 -> 107 | B27: =Correntes_PFD!C11 -> 747.22797 | C27: =Correntes_PFD!B11 -> CH4 no biogas
A28: =Correntes_PFD!A12 -> 108 | B28: =Correntes_PFD!C12 -> 1193.1543 | C28: =Correntes_PFD!B12 -> CO2 no biogas
A29: =Correntes_PFD!A13 -> 109 | B29: =Correntes_PFD!C13 -> 14742.736 | C29: =Correntes_PFD!B13 -> Digestato desaguado (torta)
A30: =Correntes_PFD!A14 -> 110 | B30: =Correntes_PFD!C14 -> 85543.192 | C30: =Correntes_PFD!B14 -> Agua separada do digestato

Sheet Resumo_Executivo
A1: Resumo Executivo - Biogas por Codigestao Anaerobia
A2: Leitura rapida para apresentacao academica ou profissional.
A4: Bloco | B4: Mensagem | C4: Valor | D4: Unidade
A5: Base | B5: Volume de mistura/dia | C5: =Premissas!C5 -> 100 | D5: m3/dia
A6: Massa | B6: Massa total de entrada | C6: =Calculos_Massa!B11 -> 102270 | D6: kg/dia
A7: Organica | B7: Solidos volateis de entrada | C7: =Calculos_Massa!B19 -> 5116.1925 | D7: kg/dia
A8: C/N | B8: Relacao C/N (catalogo) | C8: =Calculos_Massa!B20 -> 24.633663 | D8: -
A9: C/N elem. | B9: Relacao C/N (elementar) | C9: =Fechamento_Elementar!B12 -> 12.979325 | D9: -
A10: Biogas | B10: Volume de biogas | C10: =Calculos_Massa!B22 -> 1688.3435 | D10: Nm3/dia
A11: Metano | B11: Volume de metano | C11: =Calculos_Massa!B23 -> 1046.773 | D11: Nm3/dia
A12: Energia | B12: Energia no biogas (PCI) | C12: =Balanco_Energia!B9 -> 37474.473 | D12: MJ/dia
A13: Potencia | B13: Potencia eletrica media | C13: =Balanco_Energia!B16 -> 156.57737 | D13: kW
A14: Eletricidade | B14: Eletricidade liquida | C14: =Balanco_Energia!B15 -> 3757.8569 | D14: kWh/dia
A15: Termica | B15: Excedente termico | C15: =Balanco_Energia!B13 -> 12059.336 | D15: MJ/dia
A16: Digestato | B16: Massa de digestato | C16: =Calculos_Massa!B38 -> 100285.93 | D16: kg/dia
A17: Reator | B17: Volume do reator | C17: =Calculos_Massa!B33 -> 2000 | D17: m3
A18: Checks | B18: Verificacoes OK | C18: =COUNTIF(Verificacoes!E5:E14,"OK")+COUNTIF(Verificacoes!E5:E14,"OK - autossuficiente") -> 10 | D18: de 10
A21: Mensagens para apresentacao
A22: ="O digestor recebe "&FIXED(Premissas!C5,0,TRUE)&" m3/dia de mistura ("&FIXED(Calculos_Massa!B11,0,TRUE)&" kg/dia) com C/N de "&FIXED(Calculos_Massa!B20,1,TRUE)&"." -> O digestor recebe 100 m3/dia de mistura (102270 kg/dia) com C/N de 24,6.
A23: ="Produz "&FIXED(Calculos_Massa!B22,0,TRUE)&" Nm3/dia de biogas contendo "&FIXED(Calculos_Massa!B23,0,TRUE)&" Nm3/dia de metano ("&FIXED(Premissas!C41,0,TRUE)&"% CH4)." -> Produz 1688 Nm3/dia de biogas contendo 1047 Nm3/dia de metano (62% CH4).
A24: ="A cogeracao gera "&FIXED(Balanco_Energia!B15,0,TRUE)&" kWh/dia de eletricidade liquida ("&FIXED(Balanco_Energia!B16,1,TRUE)&" kW medio) e o sistema e termicamente autossuficiente." -> A cogeracao gera 3758 kWh/dia de eletricidade liquida (156,6 kW medio) e o sistema e termicamente autossuficiente.
A25: ="O fechamento elementar rastreia C/H/O/N/S desde a entrada ate biogas e digestato." -> O fechamento elementar rastreia C/H/O/N/S desde a entrada ate biogas e digestato.

Sheet KPIs
A1: Indicadores-chave de desempenho (KPIs)
A3: KPI | B3: Valor | C3: Unidade
A4: Volume de biogas | B4: =Calculos_Massa!B22 -> 1688.3435 | C4: Nm3/dia
A5: Volume de metano | B5: =Calculos_Massa!B23 -> 1046.773 | C5: Nm3/dia
A6: C/N da mistura | B6: =Calculos_Massa!B20 -> 24.633663 | C6: -
A7: COV | B7: =Calculos_Massa!B34 -> 2.5580963 | C7: kgSV/m3.dia
A8: Eficiencia remocao SV | B8: =Premissas!C39 -> 55 | C8: %
A9: Eletricidade liquida | B9: =Balanco_Energia!B15 -> 3757.8569 | C9: kWh/dia
A10: Potencia media | B10: =Balanco_Energia!B16 -> 156.57737 | C10: kW
A11: Excedente termico | B11: =Balanco_Energia!B13 -> 12059.336 | C11: MJ/dia
A12: Energia no biogas | B12: =Balanco_Energia!B9 -> 37474.473 | C12: MJ/dia
A13: Massa de digestato | B13: =Calculos_Massa!B38 -> 100285.93 | C13: kg/dia
A14: Volume do reator | B14: =Calculos_Massa!B33 -> 2000 | C14: m3
A15: C no biogas (%) | B15: =Fechamento_Elementar!B15 -> 35.844814 | C15: %
A16: Saldo operacional diario | B16: =Custos!E11 -> -859.81096 | C16: R$/dia
A17: Verificacoes OK | B17: =COUNTIF(Verificacoes!E5:E14,"OK")+COUNTIF(Verificacoes!E5:E14,"OK - autossuficiente") -> 10 | C17: de 10

Sheet Dashboard
A1: Dashboard - Biogas por Codigestao Anaerobia
A2: Indicadores visuais, graficos e leitura executiva. | Q2: CH4 (kg/dia) | R2: =Calculos_Massa!B27 -> 747.22797
Q3: CO2 (kg/dia) | R3: =Calculos_Massa!B29 -> 1193.1543
A4: ="Biogas"&CHAR(10)&FIXED(KPIs!B4,0,TRUE)&" Nm3/dia" -> Biogas 1688 Nm3/dia | E4: ="Metano"&CHAR(10)&FIXED(KPIs!B5,0,TRUE)&" Nm3/dia" -> Metano 1047 Nm3/dia | I4: ="C/N Mistura"&CHAR(10)&FIXED(KPIs!B6,1,TRUE) -> C/N Mistura 24,6 | M4: ="COV"&CHAR(10)&FIXED(KPIs!B7,2,TRUE)&" kgSV/m3.dia" -> COV 2,56 kgSV/m3.dia | Q4: Outros (kg/dia) | R4: =Calculos_Massa!B31 -> 43.688732
Q6: SV removido | R6: =Calculos_Massa!B21 -> 2813.9059
Q7: SV residual | R7: =Calculos_Massa!B35 -> 2302.2866
A9: ="Eletricidade liq."&CHAR(10)&FIXED(KPIs!B9,0,TRUE)&" kWh/dia" -> Eletricidade liq. 3758 kWh/dia | E9: ="Potencia media"&CHAR(10)&FIXED(KPIs!B10,1,TRUE)&" kW" -> Potencia media 156,6 kW | I9: ="Digestato"&CHAR(10)&FIXED(KPIs!B13,0,TRUE)&" kg/dia" -> Digestato 100286 kg/dia | M9: ="Saldo R$/dia"&CHAR(10)&FIXED(KPIs!B16,2,TRUE) -> Saldo R$/dia -859,81 | Q9: Aquecimento | R9: =Balanco_Energia!B5 -> 6136.2
Q10: Perdas | R10: =Balanco_Energia!B6 -> 920.43
Q11: Reacao (credito) | R11: =Balanco_Energia!B7 -> 3376.6871
Q12: Excedente CHP | R12: =Balanco_Energia!B13 -> 12059.336
A14: Leitura executiva | Q14: C no biogas | R14: =Fechamento_Elementar!F5 -> 885.82671
A15: ="O processo recebe "&FIXED(Premissas!C5,0,TRUE)&" m3/dia de mistura e gera "&FIXED(KPIs!B4,0,TRUE)&" Nm3/dia de biogas com "&FIXED(Premissas!C41,0,TRUE)&"% de metano." -> O processo recebe 100 m3/dia de mistura e gera 1688 Nm3/dia de biogas com 62% de metano. | Q15: C no digestato | R15: =Fechamento_Elementar!G5 -> 1585.4561
A16: ="A cogeracao produz "&FIXED(KPIs!B9,0,TRUE)&" kWh/dia de eletricidade liquida ("&FIXED(KPIs!B10,1,TRUE)&" kW medio) e o sistema e termicamente autossuficiente." -> A cogeracao produz 3758 kWh/dia de eletricidade liquida (156,6 kW medio) e o sistema e termicamente autossuficiente. | Q16: H no biogas | R16: =Fechamento_Elementar!F6 -> 186.80699
A17: ="O fechamento elementar mostra que "&FIXED(KPIs!B15,1,TRUE)&"% do carbono de entrada sai como biogas." -> O fechamento elementar mostra que 35,8% do carbono de entrada sai como biogas. | Q17: H no digestato | R17: =Fechamento_Elementar!G6 -> 158.41902
Q19: Lodo (SV) | R19: =Calculos_Massa!B16 -> 1160.25
Q20: Vinhaca (SV) | R20: =Calculos_Massa!B17 -> 385.9425
Q21: Residuo (SV) | R21: =Calculos_Massa!B18 -> 3570
Q23: Descarte digestato | R23: =Custos!E5 -> 1105.7052
Q24: Consumo eletrico | R24: =Custos!E6 -> 148.33646
Q25: Receita eletricidade | R25: =ABS(Custos!E7) -> 2818.3926
Q26: Outros custos | R26: =Custos!E8+Custos!E9 -> 704.54

Sheet Secagem_Digestato
A1: Secagem / Desaguamento do digestato
A2: Estimativa de massas apos separacao solido-liquido.
A4: Grandeza | B4: Valor | C4: Unidade | D4: Mini-resumo
A5: Massa digestato bruto | B5: =Calculos_Massa!B38 -> 100285.93 | C5: kg/dia | D5: Tudo que sai do digestor (menos o gas).
A6: ST no digestato | B6: =Calculos_Massa!B37 -> 3685.6841 | C6: kg/dia | D6: Solidos totais na saida.
A7: SV no digestato | B7: =Calculos_Massa!B35 -> 2302.2866 | C7: kg/dia | D7: Materia organica residual.
A8: SF no digestato | B8: =Calculos_Massa!B36 -> 1383.3975 | C8: kg/dia | D8: Cinzas e minerais.
A9: Agua no digestato | B9: =B5-B6 -> 96600.245 | C9: kg/dia | D9: Massa total menos solidos.
A10: % ST no digestato | B10: =B6/B5*100 -> 3.6751757 | C10: % | D10: Concentracao de solidos.
A11: ST alvo apos desaguamento | B11: =Premissas!C53 -> 25 | C11: % | D11: Premissa: 25% ST na torta.
A12: Massa torta desaguada | B12: =B6/(B11/100) -> 14742.736 | C12: kg/dia | D12: ST dividido pela concentracao alvo.
A13: Agua na torta | B13: =B12-B6 -> 11057.052 | C13: kg/dia | D13: Agua retida na torta.
A14: Agua separada (filtrado) | B14: =B9-B13 -> 85543.192 | C14: kg/dia | D14: Filtrado para tratamento ou reuso.
A15: Massa filtrado total | B15: =B5-B12 -> 85543.192 | C15: kg/dia | D15: Digestato - torta.

Sheet Dimensionamento
A1: Dimensionamento de equipamentos
A2: Calculo de dimensoes principais de cada equipamento com formulas automaticas.
A4: Tag | B4: Equipamento | C4: Variavel dimensionamento | D4: Formula | E4: Valor | F4: Unidade | G4: Margem | H4: Valor final
A5: TQ-101 | B5: Tanque mistura | C5: Volume util | D5: Q_tot * t_ret (12h) | E5: =Premissas!C5*0.5 -> 50 | F5: m3 | G5: 0.2 | H5: =E5*1.2 -> 60
A6: TQ-101 | C6: Diametro (H/D=1) | D6: (4V/pi)^(1/3) | E6: =(4*H5/3.14159)^(1/3) -> 4.2431389 | F6: m
A7: TQ-101 | C7: Altura | D7: =D -> #NAME? | E7: =E6 -> 4.2431389 | F7: m
A8: TQ-101 | C8: Potencia agitador | D8: 0.5 kW/m3 | E8: =0.5*H5 -> 30 | F8: kW
A9: D-101 | B9: Digestor anaerobio | C9: Volume util | D9: Q_tot * TRH | E9: =Premissas!C5*Premissas!C38 -> 2000 | F9: m3 | G9: 15% headspace | H9: =E9*1.15 -> 2300
A10: D-101 | C10: Diametro (H/D=1.5) | D10: (4V/(1.5*pi))^(1/3) | E10: =(4*E9/(1.5*3.14159))^(1/3) -> 11.92934 | F10: m
A11: D-101 | C11: H liquido | D11: 1.5*D | E11: =1.5*E10 -> 17.89401 | F11: m
A12: D-101 | C12: H headspace | D12: ~3 m | E12: =3 -> 3 | F12: m
A13: D-101 | C13: H total | D13: H_liq + H_head | E13: =E11+E12 -> 20.89401 | F13: m
A14: D-101 | C14: V real (check) | D14: pi/4*D^2*H_liq | E14: =3.14159/4*E10^2*E11 -> 2000 | F14: m3
A15: D-101 | C15: Potencia agitacao | D15: 5-10 W/m3 | E15: =0.01*E9 -> 20 | F15: kW
A16: D-101 | C16: Espessura minima | D16: ASME VIII: P*R/(S*E-0.6P) | E16: =(0.00507*E10/2*1000)/(137.9*0.85-0.6*0.00507) -> 0.25800163 | F16: mm | G16: + 3mm corrosao | H16: =MAX(E16,6.35)+3 -> 9.35
A17: TC-101 | B17: Trocador de calor | C17: Carga termica | D17: M*Cp*DT/1000 | E17: =Calculos_Massa!B11*Premissas!C44*(Premissas!C37-Premissas!C36)/1000 -> 6136.2 | F17: MJ/dia
A18: TC-101 | C18: Carga termica (kW) | D18: Q/(86.4) | E18: =E17/86.4 -> 71.020833 | F18: kW
A19: TC-101 | C19: LMTD (contracorrente) | D19: (DT1-DT2)/ln(DT1/DT2) | E19: =(45-30)/LN(45/30) -> 36.994552 | F19: degC
A20: TC-101 | C20: U (coeficiente global) | D20: 800 (conservador lodo) | E20: =800 -> 800 | F20: W/m2.K
A21: TC-101 | C21: Area requerida | D21: Q/(U*LMTD) | E21: =E18*1000/E20/E19 -> 2.3997058 | F21: m2 | G21: 30% fouling | H21: =E21*1.3 -> 3.1196176
A22: P-101 | B22: Bomba alimentacao | C22: Vazao | D22: Q_tot/24 | E22: =Premissas!C5/24 -> 4.1666667 | F22: m3/h
A23: P-101 | C23: dP | D23: ~2 bar | E23: =2 -> 2 | F23: bar
A24: P-101 | C24: Potencia hidraulica | D24: Q*dP | E24: =E23/3600*E24*100000 -> 0 | F24: W
A25: P-101 | C25: Potencia eixo | D25: W_hid/eta | E25: =E25/0.6 -> 0 | F25: W | G25: Motor comercial | H25: =0.75 -> 0.75
A26: P-102 | B26: Bomba digestato | C26: Vazao | D26: ~igual P-101 | E26: =Calculos_Massa!B38/1010/24 -> 4.1372083 | F26: m3/h | G26: Motor | H26: =0.75 -> 0.75
A27: FP-101 | B27: Filtro-prensa | C27: Vazao digestato | D27: massa/dia | E27: =Calculos_Massa!B38 -> 100285.93 | F27: kg/dia
A28: FP-101 | C28: Area filtracao | D28: ~100 m2 (literatura) | E28: =100 -> 100 | F28: m2
A29: FP-101 | C29: Pressao operacao | D29: 6-15 bar | E29: =10 -> 10 | F29: bar
A30: MG-101 | B30: Motor-gerador CHP | C30: Combustivel | D30: Biogas | E30: =Calculos_Massa!B22 -> 1688.3435 | F30: Nm3/dia
A31: MG-101 | C31: Energia quimica | D31: V_CH4*PCI | E31: =Calculos_Massa!B23*Premissas!C46 -> 37474.473 | F31: MJ/dia
A32: MG-101 | C32: Potencia eletrica bruta | D32: E*eta_el/86.4 | E32: =E33*Premissas!C47/86.4 -> 0 | F32: kW
A33: MG-101 | C33: Potencia eletrica liq | D33: bruta*(1-aux) | E33: =E34*(1-Premissas!C49) -> 0 | F33: kW | G33: Nominal | H33: =200 -> 200
A34: MG-101 | C34: Potencia termica | D34: E*eta_th/86.4 | E34: =E33*Premissas!C48/86.4 -> 0 | F34: kW
A35: TQ-102 | B35: Gasometro | C35: Volume buffer 6h | D35: Q_bg/24*6 | E35: =Calculos_Massa!B22/24*6 -> 422.08588 | F35: Nm3
A36: DS-101 | B36: Dessulfurizador | C36: Vazao biogas | D36: Q_bg/24 | E36: =Calculos_Massa!B22/24 -> 70.347647 | F36: Nm3/h
A37: DS-101 | C37: EBCT | D37: 3 min | E37: =3 -> 3 | F37: min
A38: DS-101 | C38: Volume carvao | D38: Q*EBCT/60 | E38: =E38/60*E39 -> 0 | F38: m3
A39: DS-101 | C39: Diametro torre | D39: ~1 m | E39: =1 -> 1 | F39: m
A40: DS-101 | C40: Altura leito | D40: V/(pi/4*D^2) | E40: =E40/(3.14159/4*E41^2) -> 0 | F40: m
A41: TQ-103 | B41: Tanque NaOH | C41: Volume | D41: 1-2 m3 reserva | E41: =2 -> 2 | F41: m3

Sheet Materiais
A1: Selecao de materiais de construcao
A2: Criterios de corrosao, abrasao e compatibilidade quimica para cada equipamento.
A4: Tag | B4: Equipamento | C4: Material corpo | D4: Material interno | E4: Justificativa | F4: Norma
A5: TQ-101 | B5: Tanque mistura | C5: Aco carbono A36 | D5: Rev. epoxi | E5: pH acido da vinhaca; baixa pressao | F5: ASTM A36
A6: P-101 | B6: Bomba alimentacao | C6: Ferro fundido | D6: Rotor inox 316L | E6: Abrasao do lodo; solidos | F6: ASTM A743
A7: TC-101 | B7: Trocador de calor | C7: Aco carbono (casco) | D7: Inox 316L (tubos) | E7: H2S dissolvido no lodo | F7: ASTM A312
A8: D-101 | B8: Digestor | C8: Aco carbono A516 Gr.70 | D8: Rev. epoxi + zona gas 316L | E8: H2S no headspace; pressao | F8: ASME VIII / NACE
A9: P-102 | B9: Bomba digestato | C9: Ferro fundido | D9: Rotor inox 316L | E9: Abrasao + H2S residual | F9: ASTM A743
A10: FP-101 | B10: Filtro-prensa | C10: Aco carbono | D10: Placas polipropileno | E10: Contato com lodo; quimicos | F10: NBR 7821
A11: MG-101 | B11: Motor-gerador | C11: Padrao fabricante | D11: N/A | E11: Biogas tratado (H2S < 200 ppm) | F11: ISO
A12: TQ-102 | B12: Gasometro | C12: Estrutura aco | D12: Membrana EPDM | E12: Biogas umido; flexibilidade | F12: NR-20
A13: DS-101 | B13: Dessulfurizador | C13: PRFV | D13: Carvao ativado | E13: H2S concentrado no gas | F13: ASTM D3299
A14: TQ-103 | B14: Tanque NaOH | C14: PEAD | D14: N/A | E14: NaOH 50%; quimico agressivo | F14: ASTM D1998
A16: Agentes de corrosao no processo
A17: Agente | B17: Onde aparece | C17: Efeito | D17: Gravidade
A18: H2S | B18: Biogas, headspace, fase liquida | C18: Pitting em aco carbono | D18: Alta
A19: CO2 dissolvido | B19: Fase liquida | C19: Corrosao acida leve | D19: Media
A20: Acidos organicos volateis | B20: Fase liquida | C20: Corrosao acida | D20: Media
A21: Abrasao por solidos | B21: Bombas, tubulacoes | C21: Desgaste mecanico | D21: Alta em pontos
A22: pH acido (vinhaca) | B22: Entrada, TQ-101 | C22: Ataque acido | D22: Media
A23: Cloretos | B23: Se agua salobra | C23: Pitting em inox 304 | D23: Media

Sheet Otimizacao
A1: Analise de sensibilidade e otimizacao
A2: Efeito das proporcoes de mistura, TRH e temperatura nos resultados do processo.
A4: Cenarios de proporcao (x_L : x_V : x_R)
A5: Cenario | B5: x_L | C5: x_V | D5: x_R | E5: SV (kg/dia) | F5: C/N | G5: Biogas (Nm3/dia) | H5: CH4 (Nm3/dia) | I5: Eletric. (kWh/dia) | J5: COV (kgSV/m3.dia)
A6: A - Base | B6: 0.5 | C6: 0.3 | D6: 0.2 | E6: =B6*Premissas!C5*Premissas!C9*Premissas!C12/100*Premissas!C15/100+C6*Premissas!C5*Premissas!C10*Premissas!C13/100*Premissas!C16/100+D6*Premissas!C5*Premissas!C11*Premissas!C14/100*Premissas!C17/100 -> 5116.1925 | F6: =(B6*Premissas!C5*Premissas!C9*Premissas!C12/100*Premissas!C15/100*Premissas!C18+C6*Premissas!C5*Premissas!C10*Premissas!C13/100*Premissas!C16/100*Premissas!C19+D6*Premissas!C5*Premissas!C11*Premissas!C14/100*Premissas!C17/100*Premissas!C20)/E6 -> 24.633663 | G6: =E6*Premissas!C39/100*Premissas!C40 -> 1688.3435 | H6: =G6*Premissas!C41/100 -> 1046.773 | I6: =H6*Premissas!C46*Premissas!C47/3.6 -> 3955.6388 | J6: =E6/Calculos_Massa!B33 -> 2.5580963
A7: B - Mais lodo | B7: 0.6 | C7: 0.2 | D7: 0.2 | E7: =B7*Premissas!C5*Premissas!C9*Premissas!C12/100*Premissas!C15/100+C7*Premissas!C5*Premissas!C10*Premissas!C13/100*Premissas!C16/100+D7*Premissas!C5*Premissas!C11*Premissas!C14/100*Premissas!C17/100 -> 5219.595 | F7: =(B7*Premissas!C5*Premissas!C9*Premissas!C12/100*Premissas!C15/100*Premissas!C18+C7*Premissas!C5*Premissas!C10*Premissas!C13/100*Premissas!C16/100*Premissas!C19+D7*Premissas!C5*Premissas!C11*Premissas!C14/100*Premissas!C17/100*Premissas!C20)/E7 -> 23.885143 | G7: =E7*Premissas!C39/100*Premissas!C40 -> 1722.4664 | H7: =G7*Premissas!C41/100 -> 1067.9291 | I7: =H7*Premissas!C46*Premissas!C47/3.6 -> 4035.5855 | J7: =E7/Calculos_Massa!B33 -> 2.6097975
A8: C - Mais residuo | B8: 0.4 | C8: 0.2 | D8: 0.4 | E8: =B8*Premissas!C5*Premissas!C9*Premissas!C12/100*Premissas!C15/100+C8*Premissas!C5*Premissas!C10*Premissas!C13/100*Premissas!C16/100+D8*Premissas!C5*Premissas!C11*Premissas!C14/100*Premissas!C17/100 -> 8325.495 | F8: =(B8*Premissas!C5*Premissas!C9*Premissas!C12/100*Premissas!C15/100*Premissas!C18+C8*Premissas!C5*Premissas!C10*Premissas!C13/100*Premissas!C16/100*Premissas!C19+D8*Premissas!C5*Premissas!C11*Premissas!C14/100*Premissas!C17/100*Premissas!C20)/E8 -> 27.392723 | G8: =E8*Premissas!C39/100*Premissas!C40 -> 2747.4133 | H8: =G8*Premissas!C41/100 -> 1703.3963 | I8: =H8*Premissas!C46*Premissas!C47/3.6 -> 6436.9453 | J8: =E8/Calculos_Massa!B33 -> 4.1627475
A9: D - Mais vinhaca | B9: 0.4 | C9: 0.4 | D9: 0.2 | E9: =B9*Premissas!C5*Premissas!C9*Premissas!C12/100*Premissas!C15/100+C9*Premissas!C5*Premissas!C10*Premissas!C13/100*Premissas!C16/100+D9*Premissas!C5*Premissas!C11*Premissas!C14/100*Premissas!C17/100 -> 5012.79 | F9: =(B9*Premissas!C5*Premissas!C9*Premissas!C12/100*Premissas!C15/100*Premissas!C18+C9*Premissas!C5*Premissas!C10*Premissas!C13/100*Premissas!C16/100*Premissas!C19+D9*Premissas!C5*Premissas!C11*Premissas!C14/100*Premissas!C17/100*Premissas!C20)/E9 -> 25.413063 | G9: =E9*Premissas!C39/100*Premissas!C40 -> 1654.2207 | H9: =G9*Premissas!C41/100 -> 1025.6168 | I9: =H9*Premissas!C46*Premissas!C47/3.6 -> 3875.6921 | J9: =E9/Calculos_Massa!B33 -> 2.506395
A10: E - Max biogas | B10: 0.3 | C10: 0.3 | D10: 0.4 | E10: =B10*Premissas!C5*Premissas!C9*Premissas!C12/100*Premissas!C15/100+C10*Premissas!C5*Premissas!C10*Premissas!C13/100*Premissas!C16/100+D10*Premissas!C5*Premissas!C11*Premissas!C14/100*Premissas!C17/100 -> 8222.0925 | F10: =(B10*Premissas!C5*Premissas!C9*Premissas!C12/100*Premissas!C15/100*Premissas!C18+C10*Premissas!C5*Premissas!C10*Premissas!C13/100*Premissas!C16/100*Premissas!C19+D10*Premissas!C5*Premissas!C11*Premissas!C14/100*Premissas!C17/100*Premissas!C20)/E10 -> 27.902601 | G10: =E10*Premissas!C39/100*Premissas!C40 -> 2713.2905 | H10: =G10*Premissas!C41/100 -> 1682.2401 | I10: =H10*Premissas!C46*Premissas!C47/3.6 -> 6356.9985 | J10: =E10/Calculos_Massa!B33 -> 4.1110463
A13: Efeito do TRH
A14: TRH (dias) | B14: V reator (m3) | C14: eta_SV (%) | D14: Biogas (Nm3/dia) | E14: COV (kgSV/m3.dia)
A15: 15 | B15: =Premissas!C5*A15 -> 1500 | C15: 52.5 | D15: =Calculos_Massa!B19*C15/100*Premissas!C40 -> 1611.6006 | E15: =Calculos_Massa!B19/B15 -> 3.410795
A16: 20 | B16: =Premissas!C5*A16 -> 2000 | C16: 60 | D16: =Calculos_Massa!B19*C16/100*Premissas!C40 -> 1841.8293 | E16: =Calculos_Massa!B19/B16 -> 2.5580963
A17: 25 | B17: =Premissas!C5*A17 -> 2500 | C17: 67.5 | D17: =Calculos_Massa!B19*C17/100*Premissas!C40 -> 2072.058 | E17: =Calculos_Massa!B19/B17 -> 2.046477
A18: 30 | B18: =Premissas!C5*A18 -> 3000 | C18: 75 | D18: =Calculos_Massa!B19*C18/100*Premissas!C40 -> 2302.2866 | E18: =Calculos_Massa!B19/B18 -> 1.7053975
A21: Efeito da temperatura
A22: Regime | B22: T (degC) | C22: eta_SV (%) | D22: Y_bg (Nm3/kgSV) | E22: Biogas (Nm3/dia) | F22: Q aquec (MJ/dia)
A23: Mesofilico | B23: 35 | C23: 55 | D23: 0.6 | E23: =Calculos_Massa!B19*C23/100*D23 -> 1688.3435 | F23: =Calculos_Massa!B11*Premissas!C44*(B23-Premissas!C36)/1000 -> 6136.2
A24: Termofilico | B24: 55 | C24: 65 | D24: 0.65 | E24: =Calculos_Massa!B19*C24/100*D24 -> 2161.5913 | F24: =Calculos_Massa!B11*Premissas!C44*(B24-Premissas!C36)/1000 -> 14317.8

Sheet CAPEX
A1: CAPEX - Investimento fixo
A2: Estimativa de ordem de grandeza. Nivel C (Towler & Sinnott, 2012).
A4: Tag | B4: Equipamento | C4: Dimensao | D4: Custo FOB (R$) | E4: Mini-resumo
A5: TQ-101 | B5: Tanque mistura 60 m3 | C5: =Dimensionamento!H5 -> 60 | D5: =80000 -> 80000 | E5: Aco carbono + epoxi
A6: P-101 | B6: Bomba cavidade 0.75 kW | C6: =Dimensionamento!H26 -> 0.75 | D6: =15000 -> 15000 | E6: Ferro fundido / 316L
A7: TC-101 | B7: Trocador espiral 3.1 m2 | C7: =Dimensionamento!H21 -> 3.1196176 | D7: =50000 -> 50000 | E7: 316L / aco carbono
A8: D-101 | B8: Digestor 2300 m3 | C8: =Dimensionamento!H9 -> 2300 | D8: =2500000 -> 2500000 | E8: Aco carbono + rev. epoxi
A9: P-102 | B9: Bomba digestato 0.75 kW | C9: =Dimensionamento!H27 -> 0 | D9: =15000 -> 15000 | E9: Ferro fundido / 316L
A10: FP-101 | B10: Filtro-prensa 100 m2 | C10: =Dimensionamento!E29 -> 10 | D10: =300000 -> 300000 | E10: Polipropileno / aco
A11: MG-101 | B11: Motor-gerador 200 kW | C11: =Dimensionamento!H35 -> 0 | D11: =600000 -> 600000 | E11: Padrao fabricante
A12: TQ-102 | B12: Gasometro 420 Nm3 | C12: =Dimensionamento!E37 -> 3 | D12: =150000 -> 150000 | E12: EPDM / aco
A13: DS-101 | B13: Dessulfurizador 3.5 m3 | C13: =Dimensionamento!E40 -> 0 | D13: =40000 -> 40000 | E13: PRFV / carvao
A14: TQ-103 | B14: Tanque NaOH 2 m3 | C14: =Dimensionamento!E43 -> 0 | D14: =5000 -> 5000 | E14: PEAD
A15: - | B15: Tubulacao, valvulas, instr. | C15: - | D15: =400000 -> 400000 | E15: Estimativa 10% equipamentos
A16: - | B16: Eletrica e automacao | C16: - | D16: =200000 -> 200000 | E16: Estimativa
A18: TOTAL FOB | D18: =SUM(D5:D16) -> 4355000
A20: Fator de Lang | B20: Solidos-liquidos | D20: 3.6 | E20: Towler & Sinnott (2012)
A21: Investimento total instalado | D21: =D18*D20 -> 15678000
A22: Capital de giro (15%) | D22: =D21*0.15 -> 2351700
A24: CAPEX TOTAL | D24: =D21+D22 -> 18029700

Sheet OPEX
A1: OPEX - Custo operacional anual
A2: Custos recorrentes de operacao da planta.
A4: Item | B4: Quantidade | C4: Unidade | D4: Custo unitario | E4: Custo anual (R$) | F4: Como calculou
A5: Mao de obra (4 pessoas) | B5: =4 -> 4 | C5: pessoas | D5: =120000 -> 120000 | E5: =B5*D5 -> 480000 | F5: 4 x R.000/mes x 12
A6: NaOH | B6: =100*365 -> 36500 | C6: kg/ano | D6: =4 -> 4 | E6: =B6*D6 -> 146000 | F6: 100 kg/dia x 365 x R/kg
A7: Carvao ativado | B7: =16*365 -> 5840 | C7: kg/ano | D7: =15 -> 15 | E7: =B7*D7 -> 87600 | F7: 16 kg/dia x R/kg
A8: Agua industrial | B8: =2.6*365 -> 949 | C8: m3/ano | D8: =10 -> 10 | E8: =B8*D8 -> 9490 | F8: 2.6 m3/dia x R/m3
A9: Manutencao (3% CAPEX) | B9: =1 -> 1 | C9: - | D9: =CAPEX!D21*0.03 -> 470340 | E9: =D9 -> 470340 | F9: 3% do investimento instalado
A10: Descarte digestato | B10: =Calculos_Massa!B37*365 -> 1345274.7 | C10: kgST/ano | D10: =0.3 -> 0.3 | E10: =B10*D10 -> 403582.41 | F10: ST x R.30/kg
A11: Seguro e impostos (2% CAPEX) | B11: =1 -> 1 | C11: - | D11: =CAPEX!D21*0.02 -> 313560 | E11: =D11 -> 313560 | F11: 2% do investimento instalado
A13: TOTAL OPEX anual | E13: =SUM(E5:E11) -> 1910572.4
A16: Receitas anuais
A17: Receita | B17: Quantidade | C17: Unidade | D17: Preco | E17: Valor anual (R$)
A18: Venda eletricidade | B18: =Balanco_Energia!B15*365 -> 1371617.8 | C18: kWh/ano | D18: =Premissas!C51 -> 0.75 | E18: =B18*D18 -> 1028713.3
A19: Biofertilizante (torta) | B19: =Secagem_Digestato!B12*365 -> 5381098.8 | C19: kg/ano | D19: 0.05 | E19: =B19*D19 -> 269054.94
A20: Creditos de carbono (est.) | B20: =Calculos_Massa!B23*365*0.000714 -> 272.79951 | C20: tCO2eq/ano | D20: 200 | E20: =B20*D20 -> 54559.902
A22: TOTAL RECEITAS anual | E22: =SUM(E18:E20) -> 1352328.2
A24: RESULTADO OPERACIONAL anual | E24: =E22-E13 -> -558244.25

Sheet Fluxo_Caixa
A1: Fluxo de caixa projetado (20 anos)
A2: Projecao simplificada sem inflacao, com taxa de desconto.
A4: Ano | B4: Investimento | C4: Receita | D4: OPEX | E4: Fluxo liq. | F4: Fluxo desc. | G4: VPL acum.
A5: 0 | B5: =-CAPEX!D24 -> -18029700 | C5: 0 | D5: 0 | E5: =B5+C5-D5 -> -18029700 | F5: =E5 -> -18029700 | G5: =F5 -> -18029700
A6: 1 | B6: 0 | C6: =OPEX!E22 -> 1352328.2 | D6: =OPEX!E13 -> 1910572.4 | E6: =B6+C6-D6 -> -558244.25 | F6: =E6/(1+Indicadores_Econ!B5)^A6 -> -507494.78 | G6: =G5+F6 -> -18537195
A7: 2 | B7: 0 | C7: =OPEX!E22 -> 1352328.2 | D7: =OPEX!E13 -> 1910572.4 | E7: =B7+C7-D7 -> -558244.25 | F7: =E7/(1+Indicadores_Econ!B5)^A7 -> -461358.89 | G7: =G6+F7 -> -18998554
A8: 3 | B8: 0 | C8: =OPEX!E22 -> 1352328.2 | D8: =OPEX!E13 -> 1910572.4 | E8: =B8+C8-D8 -> -558244.25 | F8: =E8/(1+Indicadores_Econ!B5)^A8 -> -419417.17 | G8: =G7+F8 -> -19417971
A9: 4 | B9: 0 | C9: =OPEX!E22 -> 1352328.2 | D9: =OPEX!E13 -> 1910572.4 | E9: =B9+C9-D9 -> -558244.25 | F9: =E9/(1+Indicadores_Econ!B5)^A9 -> -381288.34 | G9: =G8+F9 -> -19799259
A10: 5 | B10: 0 | C10: =OPEX!E22 -> 1352328.2 | D10: =OPEX!E13 -> 1910572.4 | E10: =B10+C10-D10 -> -558244.25 | F10: =E10/(1+Indicadores_Econ!B5)^A10 -> -346625.76 | G10: =G9+F10 -> -20145885
A11: 6 | B11: 0 | C11: =OPEX!E22 -> 1352328.2 | D11: =OPEX!E13 -> 1910572.4 | E11: =B11+C11-D11 -> -558244.25 | F11: =E11/(1+Indicadores_Econ!B5)^A11 -> -315114.33 | G11: =G10+F11 -> -20460999
A12: 7 | B12: 0 | C12: =OPEX!E22 -> 1352328.2 | D12: =OPEX!E13 -> 1910572.4 | E12: =B12+C12-D12 -> -558244.25 | F12: =E12/(1+Indicadores_Econ!B5)^A12 -> -286467.57 | G12: =G11+F12 -> -20747467
A13: 8 | B13: 0 | C13: =OPEX!E22 -> 1352328.2 | D13: =OPEX!E13 -> 1910572.4 | E13: =B13+C13-D13 -> -558244.25 | F13: =E13/(1+Indicadores_Econ!B5)^A13 -> -260425.06 | G13: =G12+F13 -> -21007892
A14: 9 | B14: 0 | C14: =OPEX!E22 -> 1352328.2 | D14: =OPEX!E13 -> 1910572.4 | E14: =B14+C14-D14 -> -558244.25 | F14: =E14/(1+Indicadores_Econ!B5)^A14 -> -236750.06 | G14: =G13+F14 -> -21244642
A15: 10 | B15: 0 | C15: =OPEX!E22 -> 1352328.2 | D15: =OPEX!E13 -> 1910572.4 | E15: =B15+C15-D15 -> -558244.25 | F15: =E15/(1+Indicadores_Econ!B5)^A15 -> -215227.33 | G15: =G14+F15 -> -21459869
A16: 11 | B16: 0 | C16: =OPEX!E22 -> 1352328.2 | D16: =OPEX!E13 -> 1910572.4 | E16: =B16+C16-D16 -> -558244.25 | F16: =E16/(1+Indicadores_Econ!B5)^A16 -> -195661.2 | G16: =G15+F16 -> -21655530
A17: 12 | B17: 0 | C17: =OPEX!E22 -> 1352328.2 | D17: =OPEX!E13 -> 1910572.4 | E17: =B17+C17-D17 -> -558244.25 | F17: =E17/(1+Indicadores_Econ!B5)^A17 -> -177873.82 | G17: =G16+F17 -> -21833404
A18: 13 | B18: 0 | C18: =OPEX!E22 -> 1352328.2 | D18: =OPEX!E13 -> 1910572.4 | E18: =B18+C18-D18 -> -558244.25 | F18: =E18/(1+Indicadores_Econ!B5)^A18 -> -161703.48 | G18: =G17+F18 -> -21995108
A19: 14 | B19: 0 | C19: =OPEX!E22 -> 1352328.2 | D19: =OPEX!E13 -> 1910572.4 | E19: =B19+C19-D19 -> -558244.25 | F19: =E19/(1+Indicadores_Econ!B5)^A19 -> -147003.16 | G19: =G18+F19 -> -22142111
A20: 15 | B20: 0 | C20: =OPEX!E22 -> 1352328.2 | D20: =OPEX!E13 -> 1910572.4 | E20: =B20+C20-D20 -> -558244.25 | F20: =E20/(1+Indicadores_Econ!B5)^A20 -> -133639.24 | G20: =G19+F20 -> -22275750
A21: 16 | B21: 0 | C21: =OPEX!E22 -> 1352328.2 | D21: =OPEX!E13 -> 1910572.4 | E21: =B21+C21-D21 -> -558244.25 | F21: =E21/(1+Indicadores_Econ!B5)^A21 -> -121490.21 | G21: =G20+F21 -> -22397240
A22: 17 | B22: 0 | C22: =OPEX!E22 -> 1352328.2 | D22: =OPEX!E13 -> 1910572.4 | E22: =B22+C22-D22 -> -558244.25 | F22: =E22/(1+Indicadores_Econ!B5)^A22 -> -110445.65 | G22: =G21+F22 -> -22507686
A23: 18 | B23: 0 | C23: =OPEX!E22 -> 1352328.2 | D23: =OPEX!E13 -> 1910572.4 | E23: =B23+C23-D23 -> -558244.25 | F23: =E23/(1+Indicadores_Econ!B5)^A23 -> -100405.14 | G23: =G22+F23 -> -22608091
A24: 19 | B24: 0 | C24: =OPEX!E22 -> 1352328.2 | D24: =OPEX!E13 -> 1910572.4 | E24: =B24+C24-D24 -> -558244.25 | F24: =E24/(1+Indicadores_Econ!B5)^A24 -> -91277.396 | G24: =G23+F24 -> -22699369
A25: 20 | B25: 0 | C25: =OPEX!E22 -> 1352328.2 | D25: =OPEX!E13 -> 1910572.4 | E25: =B25+C25-D25 -> -558244.25 | F25: =E25/(1+Indicadores_Econ!B5)^A25 -> -82979.451 | G25: =G24+F25 -> -22782348

Sheet Indicadores_Econ
A1: Indicadores economicos
A2: VPL, TIR e payback do projeto.
A4: Indicador | B4: Valor | C4: Unidade/Obs
A5: Taxa de desconto | B5: 0.1 | C5: a.a. (editavel)
A6: Vida util | B6: 20 | C6: anos
A7: CAPEX total | B7: =CAPEX!D24 -> 18029700 | C7: R$
A8: OPEX anual | B8: =OPEX!E13 -> 1910572.4 | C8: R$/ano
A9: Receita anual | B9: =OPEX!E22 -> 1352328.2 | C9: R$/ano
A10: Resultado operacional anual | B10: =OPEX!E24 -> -558244.25 | C10: R$/ano
A12: VPL (20 anos) | B12: =Fluxo_Caixa!G25 -> -22782348 | C12: R$
A13: TIR | B13: =IFERROR(IRR(Fluxo_Caixa!E5:E25),"N/A (negativo)") -> N/A (negativo) | C13: a.a.
A14: Payback simples | B14: =IF(OPEX!E24>0,CAPEX!D24/OPEX!E24,"Nao se paga") -> Nao se paga | C14: anos
A16: Nota: | B16: Projeto de biogas em ETE e tipicamente viabilizado por obrigacao regulatoria, subsidios e creditos de carbono, nao apenas por venda de eletricidade.
