Workbook

Sheet Premissas
A1: Premissas do modelo - Penicilina G
A3: Parametro | B3: Valor | C3: Unidade | D3: Observacao
A4: Produto final seco | B4: 1000 | C4: kg | D4: Base de calculo
A5: eta_sep | B5: 0.995 | C5: - | D5: Recuperacao na remocao de biomassa
A6: eta_ext1 | B6: 0.97 | C6: - | D6: Recuperacao na extracao primaria
A7: eta_ext2 | B7: 0.96 | C7: - | D7: Recuperacao na reextracao/purificacao
A8: eta_crist | B8: 0.98 | C8: - | D8: Recuperacao na cristalizacao/filtracao
A9: eta_dry | B9: 0.995 | C9: - | D9: Recuperacao na secagem/manuseio
A10: Titulo de penicilina no caldo | B10: 45 | C10: kg/m3 | D10: Faixa tipica industrial
A11: Densidade do caldo | B11: 1030 | C11: kg/m3 | D11: Premissa conceitual
A12: Biomassa seca no caldo | B12: 18 | C12: kg/m3 | D12: Premissa conceitual
A13: Umidade do bolo final | B13: 0.2 | C13: fracao | D13: Antes da secagem
A14: Umidade residual final | B14: 0.01 | C14: fracao | D14: Produto final
A15: Temperatura inicial | B15: 25 | C15: degC | D15: Meio antes da esterilizacao
... A55: Preco tratamento efluente liquido | B55: 0.015 | C55: R$/kg | D55: Premissa economica editavel

Sheet Calculos_Produto
A1: Calculos principais do produto
A3: Descricao | B3: Valor
A4: eta_global | B4: =Premissas!B5*Premissas!B6*Premissas!B7*Premissas!B8*Premissas!B9 -> 0.90347305
A5: Penicilina no caldo, kg | B5: =Premissas!B4/B4 -> 1106.8399
A6: Volume de caldo, m3 | B6: =B5/Premissas!B10 -> 24.596442
A7: Massa de caldo, kg | B7: =B6*Premissas!B11 -> 25334.335
A8: Biomassa seca, kg | B8: =Premissas!B12*B6 -> 442.73595
A9: Torta umida removida, kg | B9: =B8/Premissas!B24 -> 2213.6797
A10: Agua arrastada na torta, kg | B10: =B9-B8 -> 1770.9438
A11: Liquido clarificado para extracao, kg | B11: =B7-B9 -> 23120.655
A12: Penicilina apos separacao, kg | B12: =B5*Premissas!B5 -> 1101.3057
A13: Penicilina apos extracao primaria, kg | B13: =B12*Premissas!B6 -> 1068.2665
A14: Penicilina apos reextracao, kg | B14: =B13*Premissas!B7 -> 1025.5358
A15: Penicilina apos cristalizacao, kg | B15: =B14*Premissas!B8 -> 1005.0251
A16: Produto final calculado, kg | B16: =B15*Premissas!B9 -> 1000
A17: Perda total de produto, kg | B17: =B5-B16 -> 106.83987

Sheet Recuperacoes
A1: Recuperacoes por etapa
A3: Etapa | B3: Produto entrada (kg) | C3: Eficiencia | D3: Produto saida (kg) | E3: Perda (kg) | F3: Perda acumulada (kg)
A4: Caldo fermentado | B4: =Calculos_Produto!B5 -> 1106.8399 | C4: 1 | D4: =B4*C4 -> 1106.8399 | E4: =B4-D4 -> 0 | F4: =E4 -> 0
A5: Separacao de biomassa | B5: =D4 -> 1106.8399 | C5: =Premissas!B5 -> 0.995 | D5: =B5*C5 -> 1101.3057 | E5: =B5-D5 -> 5.5341994 | F5: =F4+E5 -> 5.5341994
A6: Extracao primaria | B6: =D5 -> 1101.3057 | C6: =Premissas!B6 -> 0.97 | D6: =B6*C6 -> 1068.2665 | E6: =B6-D6 -> 33.03917 | F6: =F5+E6 -> 38.57337
A7: Reextracao/purificacao | B7: =D6 -> 1068.2665 | C7: =Premissas!B7 -> 0.96 | D7: =B7*C7 -> 1025.5358 | E7: =B7-D7 -> 42.73066 | F7: =F6+E7 -> 81.30403
A8: Cristalizacao/filtracao | B8: =D7 -> 1025.5358 | C8: =Premissas!B8 -> 0.98 | D8: =B8*C8 -> 1005.0251 | E8: =B8-D8 -> 20.510717 | F8: =F7+E8 -> 101.81475
A9: Secagem final | B9: =D8 -> 1005.0251 | C9: =Premissas!B9 -> 0.995 | D9: =B9*C9 -> 1000 | E9: =B9-D9 -> 5.0251256 | F9: =F8+E9 -> 106.83987

Sheet Fermentacao
A1: Fermentacao pseudoestequiometrica
A3: Grandeza | B3: Valor
A4: n_pen, kmol | B4: =Calculos_Produto!B5/Premissas!B32 -> 3.3099278
A5: n_biomassa, kmol | B5: =Calculos_Produto!B8/Premissas!B33 -> 17.997396
A6: Substrato equivalente consumido, kg | B6: =Calculos_Produto!B5/Premissas!B27 -> 13835.498
A7: Substrato equivalente, kmol | B7: =B6/Premissas!B34 -> 76.86388
A8: Yx/s, kg/kg | B8: =Calculos_Produto!B8/B6 -> 0.032
A9: n_PAA, kmol | B9: =(1+Premissas!B28)*B4 -> 3.4754242
A10: m_PAA, kg | B10: =B9*Premissas!B35 -> 473.17901
A11: n_N biomassa, kmol | B11: =0.2*B5 -> 3.5994793
A12: n_N penicilina, kmol | B12: =2*B4 -> 6.6198557
A13: n_N total, kmol | B13: =B11+B12 -> 10.219335
A14: NH3 equivalente, kg | B14: =B13*Premissas!B36 -> 173.72869
A15: n_S penicilina, kmol | B15: =B4 -> 3.3099278
A16: Enxofre equivalente, kg | B16: =B15*Premissas!B37 -> 105.91769
A17: n_C no substrato, kmol | B17: =6*B7 -> 461.18328
A18: n_C na biomassa, kmol | B18: =B5 -> 17.997396
A19: n_C na penicilina, kmol | B19: =16*B4 -> 52.958846
A20: n_CO2 gerado, kmol | B20: =B17-B18-B19 -> 390.22704
A21: m_CO2 gerado, kg | B21: =B20*Premissas!B39 -> 17169.99
A22: n_H2O gerada, kmol | B22: =((12*B7)+(3*B13)-(1.8*B5+18*B4))/2 -> 430.52528
A23: m_H2O gerada, kg | B23: =B22*18 -> 7749.455
A24: n_O2 consumido, kmol | B24: =((0.5*B5)+(4*B4)+(2*B20)+B22-(6*B7))/2 -> 386.01724
A25: m_O2 consumido, kg | B25: =B24*Premissas!B38 -> 12352.552
A26: n_ar total, kmol | B26: =B24/Premissas!B30 -> 1838.1773
A27: Ar total, Nm3 | B27: =B26*Premissas!B31 -> 41200.907
A28: Massa de ar, kg | B28: =B26*Premissas!B40 -> 53013.034
A29: Vazao media de ar, Nm3/h | B29: =B27/Premissas!B29 -> 257.50567
A30: vvm medio | B30: =B29/(Calculos_Produto!B6*60) -> 0.17448707

Sheet Correntes_PFD
A1: Tabela de correntes - PFD
A3: Corrente | B3: Descricao | C3: Massa total (kg) | D3: Penicilina (kg) | E3: Biomassa (kg) | F3: Solvente (kg) | G3: Agua + outros (kg) | H3: Observacao
A4: 101 | B4: Caldo fermentado | C4: =Calculos_Produto!B7 -> 25334.335 | D4: =Calculos_Produto!B5 -> 1106.8399 | E4: =Calculos_Produto!B8 -> 442.73595 | F4: 0 | G4: =C4-D4-E4-F4 -> 23784.759 | H4: Saida do fermentador
A5: 102 | B5: Torta de biomassa | C5: =Calculos_Produto!B9 -> 2213.6797 | D5: =Calculos_Produto!B5-Calculos_Produto!B12 -> 5.5341994 | E5: =Calculos_Produto!B8 -> 442.73595 | F5: 0 | G5: =C5-D5-E5-F5 -> 1765.4096 | H5: Remocao de biomassa
A6: 103 | B6: Filtrado clarificado | C6: =Calculos_Produto!B11 -> 23120.655 | D6: =Calculos_Produto!B12 -> 1101.3057 | E6: 0 | F6: 0 | G6: =C6-D6 -> 22019.349 | H6: Segue para extracao
A7: 104 | B7: Solvente para extracao | C7: =Premissas!B25*Calculos_Produto!B11 -> 5780.1638 | D7: 0 | E7: 0 | F7: =C7 -> 5780.1638 | G7: 0 | H7: Acetato de butila
A8: 105 | B8: Extrato organico | C8: =D8+F8+G8 -> 7079.6368 | D8: =Calculos_Produto!B13 -> 1068.2665 | E8: 0 | F8: =C7 -> 5780.1638 | G8: =Premissas!B26*Calculos_Produto!B11 -> 231.20655 | H8: Fase organica rica
A9: 106 | B9: Rafinado aquoso | C9: =D9+G9 -> 21821.182 | D9: =Calculos_Produto!B12-Calculos_Produto!B13 -> 33.03917 | E9: 0 | F9: 0 | G9: =(Calculos_Produto!B11-Calculos_Produto!B12)-(Premissas!B26*Calculos_Produto!B11) -> 21788.143 | H9: Fase aquosa
A10: 107 | B10: Solucao purificada | D10: =Calculos_Produto!B14 -> 1025.5358 | E10: 0 | H10: Carga para cristalizacao
A11: 108 | B11: Licor mae / perdas | D11: =Calculos_Produto!B14-Calculos_Produto!B15 -> 20.510717 | E11: 0 | H11: Perda na cristalizacao
A12: 109 | B12: Cristais umidos | C12: =Secagem!B5 -> 1256.2814 | D12: =Calculos_Produto!B15 -> 1005.0251 | E12: 0 | F12: 0 | G12: =Secagem!B6 -> 251.25628 | H12: Entrada do secador
A13: 110 | B13: Produto final | C13: =Secagem!B7 -> 1010.101 | D13: =Premissas!B4 -> 1000 | E13: 0 | F13: 0 | G13: =Secagem!B8 -> 10.10101 | H13: Produto seco
A14: 111 | B14: Agua evaporada | C14: =Secagem!B9 -> 241.15527 | D14: 0 | E14: 0 | F14: 0 | G14: =Secagem!B9 -> 241.15527 | H14: Saida do secador
A15: 112 | B15: Perda de penicilina na secagem | C15: =Calculos_Produto!B15-Calculos_Produto!B16 -> 5.0251256 | D15: =Calculos_Produto!B15-Calculos_Produto!B16 -> 5.0251256 | E15: 0 | F15: 0 | G15: 0 | H15: Perda de manuseio/secagem

Sheet Balanco_Energia
A1: Balanco de energia
A3: Etapa | B3: Massa (kg) | C3: Cp | D3: Tin | E3: Tout | F3: Q sensivel (kJ) | G3: Q latente (kJ) | H3: Q total (kJ) | I3: Tipo
A4: Esterilizacao | B4: =Calculos_Produto!B7 -> 25334.335 | C4: =Premissas!B18 -> 4 | D4: =Premissas!B15 -> 25 | E4: =Premissas!B16 -> 121 | F4: =B4*C4*(E4-D4) -> 9728384.6 | G4: 0 | H4: =F4+G4 -> 9728384.6 | I4: Aquecimento
A5: Resfriamento pos-esterilizacao | B5: =Calculos_Produto!B7 -> 25334.335 | C5: =Premissas!B18 -> 4 | D5: =Premissas!B16 -> 121 | E5: =Premissas!B15 -> 25 | F5: =B5*C5*(D5-E5) -> 9728384.6 | G5: 0 | H5: =F5+G5 -> 9728384.6 | I5: Resfriamento
A6: Calor da fermentacao | B6: =Calculos_Produto!B5 -> 1106.8399 | C6: 0 | D6: 0 | E6: 0 | F6: 0 | G6: 0 | H6: =Premissas!B22*Calculos_Produto!B5 -> 8854719 | I6: Resfriamento
A7: Resfriamento para extracao | B7: =Calculos_Produto!B11 -> 23120.655 | C7: =Premissas!B18 -> 4 | D7: =Premissas!B15 -> 25 | E7: =Premissas!B17 -> 5 | F7: =B7*C7*(D7-E7) -> 1849652.4 | G7: 0 | H7: =F7+G7 -> 1849652.4 | I7: Resfriamento
A8: Secagem | B8: =Secagem!B9 -> 241.15527 | C8: 0 | D8: 0 | E8: 0 | F8: 0 | G8: =Secagem!B10 -> 602888.18 | H8: =F8+G8 -> 602888.18 | I8: Aquecimento
A10: Vapor teorico, kg | B10: =H4/Premissas!B20 -> 4567.3167
A11: Vapor real, kg | B11: =B10/Premissas!B23 -> 5373.3138

Sheet Secagem
A1: Calculos da secagem
A3: Grandeza | B3: Valor
A4: Solido seco antes do secador, kg | B4: =Calculos_Produto!B15 -> 1005.0251
A5: Massa total do bolo, kg | B5: =B4/(1-Premissas!B13) -> 1256.2814
A6: Agua no bolo, kg | B6: =B5-B4 -> 251.25628
A7: Massa final umida, kg | B7: =Premissas!B4/(1-Premissas!B14) -> 1010.101
A8: Agua final residual, kg | B8: =B7-Premissas!B4 -> 10.10101
A9: Agua evaporada, kg | B9: =B6-B8 -> 241.15527
A10: Carga de secagem, kJ | B10: =B9*Premissas!B21 -> 602888.18

Sheet Verificacoes
A1: Verificacoes de consistencia
A3: Verificacao | B3: Como foi checado | C3: Residual | D3: Unidade | E3: Leitura
A4: Fechamento do produto final | B4: Produto calculado - produto alvo | C4: =Calculos_Produto!B16-Premissas!B4 -> 0 | D4: kg | E4: =IF(ABS(C4)<=0.000001,"OK","Revisar") -> OK
A5: Fechamento de recuperacoes | B5: Produto final + perdas - produto no caldo | C5: =SUM(Recuperacoes!E5:E9)+Recuperacoes!D9-Recuperacoes!B4 -> 0 | D5: kg | E5: =IF(ABS(C5)<=0.000001,"OK","Revisar") -> OK
A6: Fechamento massa na separacao | B6: Corrente 101 - 102 - 103 | C6: =Correntes_PFD!C4-Correntes_PFD!C5-Correntes_PFD!C6 -> 0 | D6: kg | E6: =IF(ABS(C6)<=0.000001,"OK","Revisar") -> OK
A7: Fechamento massa na extracao | B7: Corrente 103 + 104 - 105 - 106 | C7: =Correntes_PFD!C6+Correntes_PFD!C7-Correntes_PFD!C8-Correntes_PFD!C9 -> 0 | D7: kg | E7: =IF(ABS(C7)<=0.000001,"OK","Revisar") -> OK
A8: Fechamento total na secagem | B8: Corrente 109 - 110 - 111 - 112 | C8: =Correntes_PFD!C12-Correntes_PFD!C13-Correntes_PFD!C14-Correntes_PFD!C15 -> 0 | D8: kg | E8: =IF(ABS(C8)<=0.000001,"OK","Revisar") -> OK
A9: Fechamento de solido na secagem | B9: Penicilina em 109 - 110 - 112 | C9: =Correntes_PFD!D12-Correntes_PFD!D13-Correntes_PFD!D15 -> 0 | D9: kg | E9: =IF(ABS(C9)<=0.000001,"OK","Revisar") -> OK
A10: Fechamento de agua na secagem | B10: Agua em 109 - 110 - 111 | C10: =Correntes_PFD!G12-Correntes_PFD!G13-Correntes_PFD!G14 -> 0 | D10: kg | E10: =IF(ABS(C10)<=0.000001,"OK","Revisar") -> OK
A11: Fechamento de carbono na fermentacao | B11: C alimentado - C em biomassa - C em penicilina - C em CO2 | C11: =Fermentacao!B17-Fermentacao!B18-Fermentacao!B19-Fermentacao!B20 -> 0 | D11: kmol C | E11: =IF(ABS(C11)<=0.000001,"OK","Revisar") -> OK
A12: Fechamento de vapor | B12: Vapor real - vapor teorico/eficiencia | C12: =Balanco_Energia!B11-(Balanco_Energia!B10/Premissas!B23) -> 0 | D12: kg | E12: =IF(ABS(C12)<=0.000001,"OK","Revisar") -> OK

Sheet Dicionario_Variaveis
A1: Dicionario de variaveis
A2: Esta aba explica o significado fisico, a unidade e o papel de cada variavel principal da planilha.
A4: Variavel | B4: Nome simples | C4: Definicao didatica | D4: Unidade | E4: Formula ou origem | F4: Onde aparece | G4: Por que importa
A5: P_final | B5: Produto final seco | C5: Massa de penicilina seca que se deseja obter ao final da campanha. | D5: kg | E5: Premissa de projeto | F5: Premissas, KPIs, Dashboard | G5: Define toda a escala do estudo.
A6: eta_sep | B6: Recuperacao na separacao | C6: Fracao de penicilina que continua no liquido apos remover a biomassa. | D6: - | E6: Premissa | F6: Premissas, Recuperacoes | G6: Mostra quanto produto se perde com a torta de biomassa.
A7: eta_ext1 | B7: Recuperacao na extracao primaria | C7: Fracao de penicilina transferida da fase aquosa para o solvente na primeira extracao. | D7: - | E7: Premissa | F7: Premissas, Recuperacoes | G7: Afeta fortemente a perda no downstream.
A8: eta_ext2 | B8: Recuperacao na purificacao | C8: Fracao de penicilina preservada na reextracao e purificacao. | D8: - | E8: Premissa | F8: Premissas, Recuperacoes | G8: Representa o desempenho da etapa de limpeza do produto.
A9: eta_crist | B9: Recuperacao na cristalizacao | C9: Fracao de penicilina que efetivamente vira cristal recuperavel. | D9: - | E9: Premissa | F9: Premissas, Recuperacoes | G9: Indica a eficiencia da etapa que transforma soluto em cristais.
A10: eta_dry | B10: Recuperacao na secagem | C10: Fracao de penicilina mantida apos secagem e manuseio final. | D10: - | E10: Premissa | F10: Premissas, Recuperacoes, Correntes_PFD | G10: Captura perdas finais de produto.
A11: C_penic | B11: Titulo no caldo | C11: Concentracao de penicilina no caldo fermentado. | D11: kg/m3 | E11: Premissa | F11: Premissas, Calculos_Produto | G11: Liga massa de produto ao volume de fermentacao.
A12: rho_broth | B12: Densidade do caldo | C12: Massa por unidade de volume do caldo fermentado. | D12: kg/m3 | E12: Premissa | F12: Premissas, Calculos_Produto | G12: Permite converter volume em massa total de caldo.
A13: C_x | B13: Concentracao de biomassa | C13: Quantidade de biomassa seca presente por volume de caldo. | D13: kg/m3 | E13: Premissa | F13: Premissas, Calculos_Produto | G13: Determina a carga de solidos que vai para a separacao.
A14: Xw_cake | B14: Umidade do bolo | C14: Fracao da massa do bolo que ainda e agua antes da secagem. | D14: - | E14: Premissa | F14: Premissas, Secagem | G14: Define quanta agua precisa ser removida.
A15: Xw_final | B15: Umidade final | C15: Fracao de agua que permanece no produto final. | D15: - | E15: Premissa | F15: Premissas, Secagem | G15: Define a massa final umida do produto.
... A46: Custo_especifico | B46: Custo por kg de produto | C46: Razao entre o custo total da campanha e a massa final produzida. | D46: R$/kg | E46: OPEX / P_final | F46: Custos, KPIs, Dashboard | G46: Mostra a intensidade economica do processo.

Sheet Conceitos
A1: Conceitos utilizados no modelo
A2: Leitura recomendada: comece por esta aba se quiser entender a intuicao fisica antes das formulas.
A4: Conceito | B4: Definicao simples | C4: Definicao tecnica | D4: Por que aparece na planilha
A5: Balanco de massa | B5: Tudo o que entra, sai, e se acumula precisa fechar. | C5: Aplicacao da conservacao da massa a um volume de controle. | D5: E a base de todas as correntes e perdas da planilha.
A6: Balanco de energia | B6: Energia nao surge do nada nem desaparece. | C6: Aplicacao da Primeira Lei da Termodinamica ao processo. | D6: Explica as cargas de aquecimento e resfriamento.
A7: Recuperacao | B7: Parte do produto que sobrevive a uma etapa. | C7: Razao entre a massa de produto na saida util e a massa de produto na entrada. | D7: Usada nas etapas de separacao, extracao, cristalizacao e secagem.
A8: Caldo fermentado | B8: Mistura liquida que sai do fermentador. | C8: Suspensao contendo agua, penicilina, biomassa e solutos dissolvidos. | D8: E o ponto de partida do downstream.
A9: Biomassa | B9: Massa do fungo crescido na fermentacao. | C9: Massa celular seca do microrganismo produtor. | D9: Precisa ser removida antes da extracao.
A10: Extracao liquido-liquido | B10: Separacao por preferencia do soluto entre duas fases. | C10: Transferencia de penicilina da fase aquosa para uma fase organica. | D10: Representa a etapa principal de recuperacao do produto.
A11: Reextracao/purificacao | B11: Nova transferencia para limpar o produto. | C11: Operacao de purificacao que reduz impurezas e prepara a cristalizacao. | D11: Melhora a qualidade e reduz contaminantes.
A12: Cristalizacao | B12: Transformacao do produto dissolvido em cristais. | C12: Operacao em que a solubilidade e reduzida para precipitar o soluto. | D12: Permite separar a penicilina como solido recuperavel.
A13: Secagem | B13: Remocao de agua do bolo cristalino. | C13: Operacao termica de evaporacao da umidade residual do produto. | D13: Entrega o produto em forma mais estavel e comercial.
A14: Pseudo-estequiometria | B14: Modelo simplificado de uma fermentacao real muito complexa. | C14: Fechamento aproximado de C, H, O e N usando reacoes globais equivalentes. | D14: Permite estimar substrato, O2, CO2 e precursor.
A15: Glicose equivalente | B15: Forma padrao de representar a alimentacao carbonada. | C15: Base de comparacao que converte diferentes fontes de carbono em um equivalente comum. | D15: Facilita o uso do rendimento Yp/s.
... A23: OPEX | B23: Custo operacional de campanha. | C23: Soma de materias-primas, utilidades e tratamento associados a uma campanha produtiva. | D23: A aba Custos foi criada para comparacao economica conceitual.

Sheet Utilidades
A1: Utilidades detalhadas
A2: Esta aba converte cargas de energia e aeracao em consumos de utilidades e custo associado.
A4: Utilidade | B4: Base fisica | C4: Quantidade | D4: Unidade | E4: Custo unitario | F4: Unidade custo | G4: Subtotal (R$) | H4: Observacao
A5: Vapor para esterilizacao | B5: Balanco_Energia!B11 | C5: =Balanco_Energia!B11 -> 5373.3138 | D5: kg | E5: =Premissas!B46 -> 0.18 | F5: R$/kg | G5: =C5*E5 -> 967.19648 | H5: Vapor real considerando eficiencia util
A6: Vapor equivalente para secagem | B6: Q secagem / lambda vapor | C6: =Balanco_Energia!H8/Premissas!B20 -> 283.04609 | D6: kg | E6: =Premissas!B46 -> 0.18 | F6: R$/kg | G6: =C6*E6 -> 50.948297 | H6: Equivalente termico para a secagem
A7: Agua de resfriamento equivalente | B7: (Q pos-ester + Q ferm)/(Cp*DeltaT) | C7: =(Balanco_Energia!H5+Balanco_Energia!H6)/(4.18*Premissas!B47)/1000 -> 444.57186 | D7: m3 | E7: =Premissas!B48 -> 4 | F7: R$/m3 | G7: =C7*E7 -> 1778.2874 | H7: Remocao de calor com agua industrial
A8: Frio industrial para extracao | B8: Carga de resfriamento para 5 degC | C8: =Balanco_Energia!H7/1000 -> 1849.6524 | D8: MJ | E8: =Premissas!B50 -> 0.08 | F8: R$/MJ | G8: =C8*E8 -> 147.97219 | H8: Uso de utilidade fria
A9: Eletricidade do soprador | B9: Ar total x potencia especifica | C9: =Fermentacao!B27/1000*Premissas!B52 -> 741.61632 | D9: kWh | E9: =Premissas!B51 -> 0.75 | F9: R$/kWh | G9: =C9*E9 -> 556.21224 | H9: Estimativa conceitual do soprador
A10: Eletricidade de agitacao | B10: Potencia x volume x tempo | C10: =Premissas!B53*Calculos_Produto!B6*Premissas!B29 -> 4722.5168 | D10: kWh | E10: =Premissas!B51 -> 0.75 | F10: R$/kWh | G10: =C10*E10 -> 3541.8876 | H10: Estimativa conceitual da agitacao
A12: Total de utilidades | G12: =SUM(G5:G10) -> 7042.5042

Sheet Custos
A1: Custos conceituais da campanha
A2: Custos editaveis e conceituais. Esta aba nao representa orcamento executivo; ela serve para comparacao de cenarios.
A4: Categoria | B4: Item | C4: Quantidade | D4: Unidade | E4: Custo unitario | F4: Unidade custo | G4: Subtotal (R$) | H4: Base
A5: Materia-prima | B5: Glicose equivalente | C5: =Fermentacao!B6 -> 13835.498 | D5: kg | E5: =Premissas!B42 -> 2.5 | F5: R$/kg | G5: =C5*E5 -> 34588.746 | H5: Consumo estimado na fermentacao
A6: Materia-prima | B6: Acido fenilacetico (PAA) | C6: =Fermentacao!B10 -> 473.17901 | D6: kg | E6: =Premissas!B43 -> 18 | F6: R$/kg | G6: =C6*E6 -> 8517.2222 | H6: Precursor da cadeia lateral
A7: Materia-prima | B7: NH3 equivalente | C7: =Fermentacao!B14 -> 173.72869 | D7: kg | E7: =Premissas!B44 -> 4.5 | F7: R$/kg | G7: =C7*E7 -> 781.77912 | H7: Nitrogenio assimilado
A8: Solvente | B8: Make-up de acetato de butila | C8: =Correntes_PFD!F7*(1-Premissas!B41) -> 289.00819 | D8: kg | E8: =Premissas!B45 -> 9 | F8: R$/kg | G8: =C8*E8 -> 2601.0737 | H8: Somente reposicao; considera reciclo
A9: Tratamento | B9: Descarte de biomassa umida | C9: =Correntes_PFD!C5 -> 2213.6797 | D9: kg | E9: =Premissas!B54 -> 0.35 | F9: R$/kg | G9: =C9*E9 -> 774.78791 | H9: Torta removida
A10: Tratamento | B10: Tratamento de efluente liquido | C10: =Correntes_PFD!C9+Correntes_PFD!C5 -> 24034.862 | D10: kg | E10: =Premissas!B55 -> 0.015 | F10: R$/kg | G10: =C10*E10 -> 360.52293 | H10: Rafinado + torta umida encaminhados a tratamento
A11: Utilidades | B11: Total de utilidades | C11: =0 -> 0 | D11: - | E11: =0 -> 0 | F11: - | G11: =Utilidades!G12 -> 7042.5042 | H11: Somatorio da aba Utilidades
A13: Custo operacional total da campanha | G13: =SUM(G5:G11) -> 54666.636
A14: Custo operacional especifico | G14: =G13/Premissas!B4 -> 54.666636 | H14: R$/kg produto

Sheet PFD_Visual
A1: PFD visual simplificado - Penicilina G
A2: Fluxograma conceitual ligado as correntes numeradas da aba Correntes_PFD. | L2: Corrente 104 Solvente de extracao
B5: F-101 Fermentador Saida 101 | G5: S-101 Separacao de biomassa Saida 103 | L5: E-101 Extracao primaria Saidas 105 e 106 | Q5: P-101 Purificacao Saida 107 | V5: CR-101 Cristalizacao Saidas 108 e 109 | AA5: D-101 Secagem Saidas 110, 111 e 112
E6: 101 -> | J6: 103 -> | O6: 105/107 -> | T6: 109 -> | Y6: -> 110
G10: Corrente 102 Torta de biomassa | V10: Corrente 108 Licor-mae / perdas | AA10: Corrente 111 Agua evaporada | AE10: Corrente 112 Perda de penicilina
B15: Corrente | C15: Descricao | D15: Massa (kg) | E15: Penicilina (kg) | F15: Biomassa (kg) | G15: Solvente (kg) | H15: Agua+outros (kg)
B16: =Correntes_PFD!A4 -> 101 | C16: =Correntes_PFD!B4 -> Caldo fermentado | D16: =Correntes_PFD!C4 -> 25334.335 | E16: =Correntes_PFD!D4 -> 1106.8399 | F16: =Correntes_PFD!E4 -> 442.73595 | G16: =Correntes_PFD!F4 -> 0 | H16: =Correntes_PFD!G4 -> 23784.759
B17: =Correntes_PFD!A13 -> 110 | C17: =Correntes_PFD!B13 -> Produto final | D17: =Correntes_PFD!C13 -> 1010.101 | E17: =Correntes_PFD!D13 -> 1000 | F17: =Correntes_PFD!E13 -> 0 | G17: =Correntes_PFD!F13 -> 0 | H17: =Correntes_PFD!G13 -> 10.10101

Sheet Resumo_Executivo
A1: Resumo Executivo - Producao de Penicilina G
A2: Leitura rapida para apresentacao: o objetivo desta aba e sintetizar o caso em linguagem gerencial sem perder o significado tecnico.
A4: Bloco | B4: Mensagem executiva | C4: Valor 1 | D4: Valor 2 | E4: Unidade | F4: Observacao
A5: Objetivo | B5: Base de calculo adotada | C5: =Premissas!B4 -> 1000 | E5: kg produto final | F5: Campanha conceitual de Penicilina G seca
A6: Recuperacao | B6: Recuperacao global estimada do processo | C6: =KPIs!B4 -> 0.90347305 | E6: % | F6: Indicador central de desempenho do downstream
A7: Escala | B7: Volume de caldo necessario | C7: =KPIs!B6 -> 24.596442 | E7: m3 | F7: Referencia para capacidade fermentativa
A8: Biomassa | B8: Biomassa seca gerada | C8: =KPIs!B7 -> 442.73595 | E8: kg | F8: Carga solida removida antes da extracao
A9: Energia | B9: Vapor real para esterilizacao | C9: =KPIs!B9 -> 5373.3138 | E9: kg | F9: Maior utilidade termica individual
A10: Energia | B10: Resfriamento total requerido | C10: =KPIs!B11 -> 20432.756 | E10: MJ | F10: Soma das principais demandas de frio
A11: Fermentacao | B11: CO2 gerado e ar total | C11: =KPIs!B12 -> 17169.99 | D11: =KPIs!B13 -> 41200.907 | E11: kg / Nm3 | F11: Indicadores de respiracao e aeracao
A12: Economia | B12: Custo total e custo especifico | C12: =KPIs!B16 -> 54666.636 | D12: =KPIs!B17 -> 54.666636 | E12: R$ / R$/kg | F12: Custos conceituais e editaveis
A13: Confiabilidade | B13: Todos os fechamentos automaticos | C13: =COUNTIF(Verificacoes!E4:E12,"OK") -> 9 | D13: =ROWS(Verificacoes!E4:E12) -> 9 | E13: checks | F13: A leitura ideal e todos os checks em OK
A16: Mensagens prontas para apresentacao
A17: ="Para produzir "&FIXED(Premissas!B4,0,TRUE)&" kg de Penicilina G seca, o modelo exige aproximadamente "&FIXED(KPIs!B6,2,TRUE)&" m3 de caldo fermentado e "&FIXED(KPIs!B7,1,TRUE)&" kg de biomassa seca gerada." -> Para produzir 1000 kg de Penicilina G seca, o modelo exige aproximadamente 24,60 m3 de caldo fermentado e 442,7 kg de biomassa seca gerada.
A18: ="A recuperacao global estimada do processo e de "&FIXED(100*KPIs!B4,1,TRUE)&"%, indicando que a principal atencao do projeto deve estar no desempenho do downstream." -> A recuperacao global estimada do processo e de 90,3%, indicando que a principal atencao do projeto deve estar no desempenho do downstream.
A19: ="Do ponto de vista energetico, o processo requer cerca de "&FIXED(KPIs!B9,1,TRUE)&" kg de vapor e "&FIXED(KPIs!B11,1,TRUE)&" MJ de resfriamento total." -> Do ponto de vista energetico, o processo requer cerca de 5373,3 kg de vapor e 20432,8 MJ de resfriamento total.
A20: ="Do ponto de vista economico, o custo operacional conceitual desta campanha e de R$ "&FIXED(KPIs!B16,2,TRUE)&", equivalente a R$ "&FIXED(KPIs!B17,2,TRUE)&" por kg de produto." -> Do ponto de vista economico, o custo operacional conceitual desta campanha e de R$ 54666,64, equivalente a R$ 54,67 por kg de produto.
A21: ="A base esta consistente no nivel conceitual: "&COUNTIF(Verificacoes!E4:E12,"OK")&" de "&ROWS(Verificacoes!E4:E12)&" verificacoes automaticas ficaram em OK." -> A base esta consistente no nivel conceitual: 9 de 9 verificacoes automaticas ficaram em OK.

Sheet KPIs
A1: Indicadores principais
A3: KPI | B3: Valor | C3: Unidade
A4: Recuperacao global | B4: =Calculos_Produto!B16/Calculos_Produto!B5 -> 0.90347305 | C4: %
A5: Penicilina no caldo | B5: =Calculos_Produto!B5 -> 1106.8399 | C5: kg
A6: Volume de caldo | B6: =Calculos_Produto!B6 -> 24.596442 | C6: m3
A7: Biomassa seca gerada | B7: =Calculos_Produto!B8 -> 442.73595 | C7: kg
A8: Perda total de produto | B8: =Calculos_Produto!B17 -> 106.83987 | C8: kg
A9: Vapor real | B9: =Balanco_Energia!B11 -> 5373.3138 | C9: kg
A10: Aquecimento total | B10: =(Balanco_Energia!H4+Balanco_Energia!H8)/1000 -> 10331.273 | C10: MJ
A11: Resfriamento total | B11: =(Balanco_Energia!H5+Balanco_Energia!H6+Balanco_Energia!H7)/1000 -> 20432.756 | C11: MJ
A12: CO2 gerado | B12: =Fermentacao!B21 -> 17169.99 | C12: kg
A13: Ar total | B13: =Fermentacao!B27 -> 41200.907 | C13: Nm3
A14: m3 caldo / kg produto | B14: =Calculos_Produto!B6/Premissas!B4 -> 0.024596442 | C14: m3/kg
A15: kg biomassa / kg produto | B15: =Calculos_Produto!B8/Premissas!B4 -> 0.44273595 | C15: kg/kg
A16: Custo total da campanha | B16: =Custos!G13 -> 54666.636 | C16: R$
A17: Custo especifico | B17: =Custos!G14 -> 54.666636 | C17: R$/kg
A18: Make-up de solvente | B18: =Custos!C8 -> 289.00819 | C18: kg
A19: Custo de utilidades | B19: =Utilidades!G12 -> 7042.5042 | C19: R$

Sheet Dashboard
A1: Dashboard - Penicilina G
A2: Versao para apresentacao: indicadores principais, distribuicoes e leitura executiva do processo. | R2: =Premissas!B4 -> 1000 | U2: =Custos!G5 -> 34588.746
R3: =Calculos_Produto!B8 -> 442.73595 | U3: =Custos!G6 -> 8517.2222
A4: ="Recuperacao Global"&CHAR(10)&FIXED(100*KPIs!B4,1,TRUE)&"%" -> Recuperacao Global 90,3% | E4: ="Penicilina no Caldo"&CHAR(10)&FIXED(KPIs!B5,1,TRUE)&" kg" -> Penicilina no Caldo 1106,8 kg | I4: ="Volume de Caldo"&CHAR(10)&FIXED(KPIs!B6,2,TRUE)&" m3" -> Volume de Caldo 24,60 m3 | M4: ="Custo Especifico"&CHAR(10)&"R$ "&FIXED(KPIs!B17,2,TRUE)&"/kg" -> Custo Especifico R$ 54,67/kg | R4: =Secagem!B9 -> 241.15527 | U4: =Custos!G7 -> 781.77912
R5: =Calculos_Produto!B17 -> 106.83987 | U5: =Custos!G8 -> 2601.0737
U6: =Custos!G9+Custos!G10 -> 1135.3108
U7: =Custos!G11 -> 7042.5042
A9: ="Vapor Real"&CHAR(10)&FIXED(KPIs!B9,1,TRUE)&" kg" -> Vapor Real 5373,3 kg | E9: ="Resfriamento Total"&CHAR(10)&FIXED(KPIs!B11,1,TRUE)&" MJ" -> Resfriamento Total 20432,8 MJ | I9: ="CO2 Gerado"&CHAR(10)&FIXED(KPIs!B12,1,TRUE)&" kg" -> CO2 Gerado 17170,0 kg | M9: ="Ar Total"&CHAR(10)&FIXED(KPIs!B13,1,TRUE)&" Nm3" -> Ar Total 41200,9 Nm3
U10: =Utilidades!G5 -> 967.19648
U11: =Utilidades!G6 -> 50.948297
U12: =Utilidades!G7 -> 1778.2874
U13: =Utilidades!G8 -> 147.97219
A14: Leitura executiva | U14: =Utilidades!G9 -> 556.21224
A15: ="O processo entrega "&FIXED(Premissas!B4,0,TRUE)&" kg de produto final com recuperacao global de "&FIXED(100*KPIs!B4,1,TRUE)&"%." -> O processo entrega 1000 kg de produto final com recuperacao global de 90,3%. | U15: =Utilidades!G10 -> 3541.8876
A16: ="Os maiores esforcos energeticos estao em esterilizacao, resfriamento pos-esterilizacao e fermentacao." -> Os maiores esforcos energeticos estao em esterilizacao, resfriamento pos-esterilizacao e fermentacao.
A17: ="O custo conceitual da campanha e de R$ "&FIXED(KPIs!B16,2,TRUE)&", com forte influencia de materias-primas e utilidades." -> O custo conceitual da campanha e de R$ 54666,64, com forte influencia de materias-primas e utilidades.
A18: ="Todos os fechamentos automaticos permanecem consistentes: "&COUNTIF(Verificacoes!E4:E12,"OK")&" verificacoes em OK." -> Todos os fechamentos automaticos permanecem consistentes: 9 verificacoes em OK.
